<?xml version="1.0" encoding="UTF-8"?>
<gpx version="1.1" creator="GPS Track Editor" xmlns="http://www.topografix.com/GPX/1/1" xmlns:xsi="http://www.w3.org/2001/XMLSchema-instance" xmlns:gte="http://www.gpstrackeditor.com/xmlschemas/General/1" xmlns:gpxtpx="http://www.garmin.com/xmlschemas/TrackPointExtension/v1" xmlns:gpxx="http://www.garmin.com/xmlschemas/GpxExtensions/v3" targetNamespace="http://www.topografix.com/GPX/1/1" elementFormDefault="qualified" xsi:schemaLocation="http://www.topografix.com/GPX/1/1 http://www.topografix.com/GPX/1/1/gpx.xsd">
<metadata>
	<name>20240623 - Bezverov - Nectiny.gpx</name>
	<desc>18,413,-633
        </desc>
	<keywords>Monca, ja</keywords>
</metadata>
<trk>
	<name>20240623 - nedele</name>
	<trkseg>
		<trkpt lat="49.994450" lon="13.060079">
			<ele>687.71</ele>
			<time>2024-06-23T07:02:11Z</time>
		</trkpt>
		<trkpt lat="49.994702" lon="13.060032">
			<ele>687.84</ele>
			<time>2024-06-23T07:02:38Z</time>
		</trkpt>
		<trkpt lat="49.994922" lon="13.060284">
			<ele>687.71</ele>
			<time>2024-06-23T07:03:00Z</time>
		</trkpt>
		<trkpt lat="49.995142" lon="13.060551">
			<ele>688.42</ele>
			<time>2024-06-23T07:03:25Z</time>
		</trkpt>
		<trkpt lat="49.995337" lon="13.060852">
			<ele>688.51</ele>
			<time>2024-06-23T07:03:43Z</time>
		</trkpt>
		<trkpt lat="49.995577" lon="13.061236">
			<ele>688.35</ele>
			<time>2024-06-23T07:04:54Z</time>
		</trkpt>
		<trkpt lat="49.995805" lon="13.061498">
			<ele>688.06</ele>
			<time>2024-06-23T07:05:33Z</time>
		</trkpt>
		<trkpt lat="49.996062" lon="13.061607">
			<ele>687.47</ele>
			<time>2024-06-23T07:05:51Z</time>
		</trkpt>
		<trkpt lat="49.996332" lon="13.061713">
			<ele>686.58</ele>
			<time>2024-06-23T07:06:12Z</time>
		</trkpt>
		<trkpt lat="49.996599" lon="13.061852">
			<ele>685.37</ele>
			<time>2024-06-23T07:06:32Z</time>
		</trkpt>
		<trkpt lat="49.996877" lon="13.061954">
			<ele>683.54</ele>
			<time>2024-06-23T07:06:55Z</time>
		</trkpt>
		<trkpt lat="49.997147" lon="13.062045">
			<ele>682.02</ele>
			<time>2024-06-23T07:07:17Z</time>
		</trkpt>
		<trkpt lat="49.997397" lon="13.061847">
			<ele>680.85</ele>
			<time>2024-06-23T07:07:38Z</time>
		</trkpt>
		<trkpt lat="49.997550" lon="13.061498">
			<ele>680.00</ele>
			<time>2024-06-23T07:08:00Z</time>
		</trkpt>
		<trkpt lat="49.997743" lon="13.061227">
			<ele>678.43</ele>
			<time>2024-06-23T07:08:21Z</time>
		</trkpt>
		<trkpt lat="49.998022" lon="13.061256">
			<ele>674.88</ele>
			<time>2024-06-23T07:08:44Z</time>
		</trkpt>
		<trkpt lat="49.998276" lon="13.061416">
			<ele>674.08</ele>
			<time>2024-06-23T07:10:08Z</time>
		</trkpt>
		<trkpt lat="49.998558" lon="13.061682">
			<ele>673.86</ele>
			<time>2024-06-23T07:10:39Z</time>
		</trkpt>
		<trkpt lat="49.998536" lon="13.062249">
			<ele>673.41</ele>
			<time>2024-06-23T07:11:12Z</time>
		</trkpt>
		<trkpt lat="49.998658" lon="13.062784">
			<ele>670.84</ele>
			<time>2024-06-23T07:11:46Z</time>
		</trkpt>
		<trkpt lat="49.998790" lon="13.063309">
			<ele>669.15</ele>
			<time>2024-06-23T07:12:18Z</time>
		</trkpt>
		<trkpt lat="49.998942" lon="13.063818">
			<ele>668.42</ele>
			<time>2024-06-23T07:12:50Z</time>
		</trkpt>
		<trkpt lat="49.999069" lon="13.064348">
			<ele>667.48</ele>
			<time>2024-06-23T07:13:23Z</time>
		</trkpt>
		<trkpt lat="49.999169" lon="13.064889">
			<ele>666.79</ele>
			<time>2024-06-23T07:13:56Z</time>
		</trkpt>
		<trkpt lat="49.999294" lon="13.065422">
			<ele>665.49</ele>
			<time>2024-06-23T07:14:29Z</time>
		</trkpt>
		<trkpt lat="49.999464" lon="13.065933">
			<ele>665.20</ele>
			<time>2024-06-23T07:15:00Z</time>
		</trkpt>
		<trkpt lat="49.999633" lon="13.066431">
			<ele>664.19</ele>
			<time>2024-06-23T07:15:52Z</time>
		</trkpt>
		<trkpt lat="49.999768" lon="13.066963">
			<ele>663.04</ele>
			<time>2024-06-23T07:16:30Z</time>
		</trkpt>
		<trkpt lat="49.999882" lon="13.067496">
			<ele>661.24</ele>
			<time>2024-06-23T07:17:00Z</time>
		</trkpt>
		<trkpt lat="50.000057" lon="13.067996">
			<ele>662.04</ele>
			<time>2024-06-23T07:17:47Z</time>
		</trkpt>
		<trkpt lat="50.000348" lon="13.068333">
			<ele>660.86</ele>
			<time>2024-06-23T07:18:15Z</time>
		</trkpt>
		<trkpt lat="50.000612" lon="13.068461">
			<ele>656.51</ele>
			<time>2024-06-23T07:18:38Z</time>
		</trkpt>
		<trkpt lat="50.000871" lon="13.068595">
			<ele>652.90</ele>
			<time>2024-06-23T07:19:00Z</time>
		</trkpt>
		<trkpt lat="50.001132" lon="13.068743">
			<ele>650.79</ele>
			<time>2024-06-23T07:19:23Z</time>
		</trkpt>
		<trkpt lat="50.001369" lon="13.068924">
			<ele>648.71</ele>
			<time>2024-06-23T07:19:53Z</time>
		</trkpt>
		<trkpt lat="50.001607" lon="13.069165">
			<ele>646.55</ele>
			<time>2024-06-23T07:20:18Z</time>
		</trkpt>
		<trkpt lat="50.001836" lon="13.069415">
			<ele>645.46</ele>
			<time>2024-06-23T07:20:42Z</time>
		</trkpt>
		<trkpt lat="50.002056" lon="13.069682">
			<ele>643.28</ele>
			<time>2024-06-23T07:21:04Z</time>
		</trkpt>
		<trkpt lat="50.002260" lon="13.069994">
			<ele>640.31</ele>
			<time>2024-06-23T07:21:25Z</time>
		</trkpt>
		<trkpt lat="50.002464" lon="13.070289">
			<ele>637.19</ele>
			<time>2024-06-23T07:21:46Z</time>
		</trkpt>
		<trkpt lat="50.002654" lon="13.070607">
			<ele>633.67</ele>
			<time>2024-06-23T07:22:09Z</time>
		</trkpt>
		<trkpt lat="50.002747" lon="13.071012">
			<ele>632.63</ele>
			<time>2024-06-23T07:22:34Z</time>
		</trkpt>
		<trkpt lat="50.002846" lon="13.071554">
			<ele>629.59</ele>
			<time>2024-06-23T07:23:04Z</time>
		</trkpt>
		<trkpt lat="50.002907" lon="13.072110">
			<ele>629.05</ele>
			<time>2024-06-23T07:23:36Z</time>
		</trkpt>
		<trkpt lat="50.003017" lon="13.072656">
			<ele>628.41</ele>
			<time>2024-06-23T07:24:05Z</time>
		</trkpt>
		<trkpt lat="50.003112" lon="13.073091">
			<ele>626.69</ele>
			<time>2024-06-23T07:24:27Z</time>
		</trkpt>
		<trkpt lat="50.003236" lon="13.073488">
			<ele>625.84</ele>
			<time>2024-06-23T07:24:51Z</time>
		</trkpt>
		<trkpt lat="50.003311" lon="13.073906">
			<ele>623.88</ele>
			<time>2024-06-23T07:25:13Z</time>
		</trkpt>
		<trkpt lat="50.003391" lon="13.074326">
			<ele>622.73</ele>
			<time>2024-06-23T07:25:33Z</time>
		</trkpt>
		<trkpt lat="50.003487" lon="13.074731">
			<ele>620.61</ele>
			<time>2024-06-23T07:25:56Z</time>
		</trkpt>
		<trkpt lat="50.003561" lon="13.075149">
			<ele>617.12</ele>
			<time>2024-06-23T07:26:20Z</time>
		</trkpt>
		<trkpt lat="50.003578" lon="13.075581">
			<ele>615.43</ele>
			<time>2024-06-23T07:26:44Z</time>
		</trkpt>
		<trkpt lat="50.003621" lon="13.076000">
			<ele>614.73</ele>
			<time>2024-06-23T07:27:04Z</time>
		</trkpt>
		<trkpt lat="50.003696" lon="13.076421">
			<ele>614.24</ele>
			<time>2024-06-23T07:27:27Z</time>
		</trkpt>
		<trkpt lat="50.003766" lon="13.076839">
			<ele>613.59</ele>
			<time>2024-06-23T07:27:49Z</time>
		</trkpt>
		<trkpt lat="50.003818" lon="13.077303">
			<ele>611.20</ele>
			<time>2024-06-23T07:28:18Z</time>
		</trkpt>
		<trkpt lat="50.003967" lon="13.077751">
			<ele>609.28</ele>
			<time>2024-06-23T07:29:03Z</time>
		</trkpt>
		<trkpt lat="50.004137" lon="13.078242">
			<ele>606.94</ele>
			<time>2024-06-23T07:29:39Z</time>
		</trkpt>
		<trkpt lat="50.004280" lon="13.078604">
			<ele>605.62</ele>
			<time>2024-06-23T07:30:07Z</time>
		</trkpt>
		<trkpt lat="50.004436" lon="13.078998">
			<ele>603.69</ele>
			<time>2024-06-23T07:30:36Z</time>
		</trkpt>
		<trkpt lat="50.004593" lon="13.079385">
			<ele>601.20</ele>
			<time>2024-06-23T07:31:14Z</time>
		</trkpt>
		<trkpt lat="50.004744" lon="13.079825">
			<ele>599.71</ele>
			<time>2024-06-23T07:31:37Z</time>
		</trkpt>
		<trkpt lat="50.004917" lon="13.080316">
			<ele>599.45</ele>
			<time>2024-06-23T07:32:08Z</time>
		</trkpt>
		<trkpt lat="50.005045" lon="13.080838">
			<ele>599.77</ele>
			<time>2024-06-23T07:32:39Z</time>
		</trkpt>
		<trkpt lat="50.005148" lon="13.081352">
			<ele>598.88</ele>
			<time>2024-06-23T07:33:06Z</time>
		</trkpt>
		<trkpt lat="50.005342" lon="13.081837">
			<ele>600.46</ele>
			<time>2024-06-23T07:33:33Z</time>
		</trkpt>
		<trkpt lat="50.005599" lon="13.082253">
			<ele>604.27</ele>
			<time>2024-06-23T07:34:04Z</time>
		</trkpt>
		<trkpt lat="50.005807" lon="13.082535">
			<ele>607.02</ele>
			<time>2024-06-23T07:34:27Z</time>
		</trkpt>
		<trkpt lat="50.006013" lon="13.082830">
			<ele>610.32</ele>
			<time>2024-06-23T07:34:51Z</time>
		</trkpt>
		<trkpt lat="50.006222" lon="13.083099">
			<ele>613.89</ele>
			<time>2024-06-23T07:35:15Z</time>
		</trkpt>
		<trkpt lat="50.006419" lon="13.083373">
			<ele>617.82</ele>
			<time>2024-06-23T07:35:42Z</time>
		</trkpt>
		<trkpt lat="50.006631" lon="13.083648">
			<ele>620.97</ele>
			<time>2024-06-23T07:36:08Z</time>
		</trkpt>
		<trkpt lat="50.006921" lon="13.084001">
			<ele>623.95</ele>
			<time>2024-06-23T07:36:39Z</time>
		</trkpt>
		<trkpt lat="50.007202" lon="13.084369">
			<ele>626.15</ele>
			<time>2024-06-23T07:37:14Z</time>
		</trkpt>
		<trkpt lat="50.007423" lon="13.084819">
			<ele>626.25</ele>
			<time>2024-06-23T07:37:48Z</time>
		</trkpt>
		<trkpt lat="50.007682" lon="13.085222">
			<ele>626.70</ele>
			<time>2024-06-23T07:38:25Z</time>
		</trkpt>
		<trkpt lat="50.007928" lon="13.085626">
			<ele>625.93</ele>
			<time>2024-06-23T07:39:01Z</time>
		</trkpt>
		<trkpt lat="50.008182" lon="13.086057">
			<ele>627.52</ele>
			<time>2024-06-23T07:39:34Z</time>
		</trkpt>
		<trkpt lat="50.008416" lon="13.086484">
			<ele>628.76</ele>
			<time>2024-06-23T07:40:03Z</time>
		</trkpt>
		<trkpt lat="50.008717" lon="13.086804">
			<ele>629.86</ele>
			<time>2024-06-23T07:40:32Z</time>
		</trkpt>
		<trkpt lat="50.008897" lon="13.087056">
			<ele>629.92</ele>
			<time>2024-06-23T07:40:50Z</time>
		</trkpt>
		<trkpt lat="50.009121" lon="13.087305">
			<ele>630.57</ele>
			<time>2024-06-23T07:41:11Z</time>
		</trkpt>
		<trkpt lat="50.009481" lon="13.087407">
			<ele>632.15</ele>
			<time>2024-06-23T07:42:38Z</time>
		</trkpt>
		<trkpt lat="50.009835" lon="13.087311">
			<ele>635.54</ele>
			<time>2024-06-23T07:43:14Z</time>
		</trkpt>
		<trkpt lat="50.010226" lon="13.087363">
			<ele>634.32</ele>
			<time>2024-06-23T07:43:43Z</time>
		</trkpt>
		<trkpt lat="50.010486" lon="13.087260">
			<ele>634.12</ele>
			<time>2024-06-23T07:44:19Z</time>
		</trkpt>
		<trkpt lat="50.010735" lon="13.087602">
			<ele>633.63</ele>
			<time>2024-06-23T07:45:52Z</time>
		</trkpt>
		<trkpt lat="50.010835" lon="13.088023">
			<ele>632.21</ele>
			<time>2024-06-23T07:46:20Z</time>
		</trkpt>
		<trkpt lat="50.010973" lon="13.088382">
			<ele>631.76</ele>
			<time>2024-06-23T07:46:38Z</time>
		</trkpt>
		<trkpt lat="50.011180" lon="13.088666">
			<ele>633.07</ele>
			<time>2024-06-23T07:46:59Z</time>
		</trkpt>
		<trkpt lat="50.011400" lon="13.088909">
			<ele>634.26</ele>
			<time>2024-06-23T07:47:22Z</time>
		</trkpt>
		<trkpt lat="50.011630" lon="13.089148">
			<ele>633.33</ele>
			<time>2024-06-23T07:47:43Z</time>
		</trkpt>
		<trkpt lat="50.011906" lon="13.089247">
			<ele>633.10</ele>
			<time>2024-06-23T07:48:08Z</time>
		</trkpt>
		<trkpt lat="50.012271" lon="13.089251">
			<ele>631.70</ele>
			<time>2024-06-23T07:49:34Z</time>
		</trkpt>
		<trkpt lat="50.012544" lon="13.089191">
			<ele>630.71</ele>
			<time>2024-06-23T07:49:58Z</time>
		</trkpt>
		<trkpt lat="50.012820" lon="13.089150">
			<ele>629.26</ele>
			<time>2024-06-23T07:50:20Z</time>
		</trkpt>
		<trkpt lat="50.013100" lon="13.089081">
			<ele>627.92</ele>
			<time>2024-06-23T07:50:42Z</time>
		</trkpt>
		<trkpt lat="50.013458" lon="13.088998">
			<ele>625.91</ele>
			<time>2024-06-23T07:51:44Z</time>
		</trkpt>
		<trkpt lat="50.013735" lon="13.088932">
			<ele>624.23</ele>
			<time>2024-06-23T07:52:08Z</time>
		</trkpt>
		<trkpt lat="50.014012" lon="13.088869">
			<ele>622.31</ele>
			<time>2024-06-23T07:52:34Z</time>
		</trkpt>
		<trkpt lat="50.014297" lon="13.088830">
			<ele>620.32</ele>
			<time>2024-06-23T07:53:00Z</time>
		</trkpt>
		<trkpt lat="50.014482" lon="13.089136">
			<ele>617.02</ele>
			<time>2024-06-23T07:53:26Z</time>
		</trkpt>
		<trkpt lat="50.014651" lon="13.089475">
			<ele>612.74</ele>
			<time>2024-06-23T07:53:49Z</time>
		</trkpt>
		<trkpt lat="50.014772" lon="13.089860">
			<ele>608.72</ele>
			<time>2024-06-23T07:54:12Z</time>
		</trkpt>
		<trkpt lat="50.014889" lon="13.090260">
			<ele>605.72</ele>
			<time>2024-06-23T07:54:34Z</time>
		</trkpt>
		<trkpt lat="50.014927" lon="13.090693">
			<ele>603.54</ele>
			<time>2024-06-23T07:54:53Z</time>
		</trkpt>
		<trkpt lat="50.015021" lon="13.091096">
			<ele>601.79</ele>
			<time>2024-06-23T07:55:17Z</time>
		</trkpt>
		<trkpt lat="50.015254" lon="13.091479">
			<ele>599.78</ele>
			<time>2024-06-23T07:55:49Z</time>
		</trkpt>
		<trkpt lat="50.015417" lon="13.091876">
			<ele>597.97</ele>
			<time>2024-06-23T07:56:09Z</time>
		</trkpt>
		<trkpt lat="50.015615" lon="13.092172">
			<ele>597.17</ele>
			<time>2024-06-23T07:56:27Z</time>
		</trkpt>
		<trkpt lat="50.015821" lon="13.092451">
			<ele>595.71</ele>
			<time>2024-06-23T07:56:51Z</time>
		</trkpt>
		<trkpt lat="50.015876" lon="13.092877">
			<ele>595.38</ele>
			<time>2024-06-23T07:57:11Z</time>
		</trkpt>
		<trkpt lat="50.015989" lon="13.093277">
			<ele>595.49</ele>
			<time>2024-06-23T07:57:30Z</time>
		</trkpt>
		<trkpt lat="50.016100" lon="13.093681">
			<ele>596.00</ele>
			<time>2024-06-23T07:57:52Z</time>
		</trkpt>
		<trkpt lat="50.016408" lon="13.093999">
			<ele>597.01</ele>
			<time>2024-06-23T07:59:01Z</time>
		</trkpt>
		<trkpt lat="50.016759" lon="13.094037">
			<ele>593.68</ele>
			<time>2024-06-23T08:00:09Z</time>
		</trkpt>
		<trkpt lat="50.016958" lon="13.094550">
			<ele>594.40</ele>
			<time>2024-06-23T08:04:10Z</time>
		</trkpt>
		<trkpt lat="50.016663" lon="13.094216">
			<ele>594.73</ele>
			<time>2024-06-23T08:08:37Z</time>
		</trkpt>
		<trkpt lat="50.016545" lon="13.094547">
			<ele>597.48</ele>
			<time>2024-06-23T08:09:41Z</time>
		</trkpt>
		<trkpt lat="50.016726" lon="13.095010">
			<ele>596.96</ele>
			<time>2024-06-23T08:10:15Z</time>
		</trkpt>
		<trkpt lat="50.016934" lon="13.095526">
			<ele>595.24</ele>
			<time>2024-06-23T08:11:02Z</time>
		</trkpt>
		<trkpt lat="50.017051" lon="13.096065">
			<ele>593.86</ele>
			<time>2024-06-23T08:11:37Z</time>
		</trkpt>
		<trkpt lat="50.017142" lon="13.096390">
			<ele>593.15</ele>
			<time>2024-06-23T08:14:56Z</time>
		</trkpt>
		<trkpt lat="50.017265" lon="13.096843">
			<ele>592.30</ele>
			<time>2024-06-23T08:15:24Z</time>
		</trkpt>
		<trkpt lat="50.017390" lon="13.097231">
			<ele>591.57</ele>
			<time>2024-06-23T08:15:49Z</time>
		</trkpt>
		<trkpt lat="50.017521" lon="13.097613">
			<ele>590.96</ele>
			<time>2024-06-23T08:16:14Z</time>
		</trkpt>
		<trkpt lat="50.017770" lon="13.097783">
			<ele>589.16</ele>
			<time>2024-06-23T08:16:46Z</time>
		</trkpt>
		<trkpt lat="50.018127" lon="13.097846">
			<ele>588.43</ele>
			<time>2024-06-23T08:18:27Z</time>
		</trkpt>
		<trkpt lat="50.018418" lon="13.097711">
			<ele>587.71</ele>
			<time>2024-06-23T08:19:45Z</time>
		</trkpt>
		<trkpt lat="50.018589" lon="13.097122">
			<ele>586.89</ele>
			<time>2024-06-23T08:22:59Z</time>
		</trkpt>
		<trkpt lat="50.018239" lon="13.097318">
			<ele>587.53</ele>
			<time>2024-06-23T08:24:18Z</time>
		</trkpt>
		<trkpt lat="50.017948" lon="13.097652">
			<ele>588.99</ele>
			<time>2024-06-23T08:25:19Z</time>
		</trkpt>
		<trkpt lat="50.017730" lon="13.097959">
			<ele>589.49</ele>
			<time>2024-06-23T08:26:59Z</time>
		</trkpt>
		<trkpt lat="50.017941" lon="13.098238">
			<ele>588.62</ele>
			<time>2024-06-23T08:27:24Z</time>
		</trkpt>
		<trkpt lat="50.018127" lon="13.098570">
			<ele>587.90</ele>
			<time>2024-06-23T08:27:47Z</time>
		</trkpt>
		<trkpt lat="50.018280" lon="13.098918">
			<ele>585.25</ele>
			<time>2024-06-23T08:28:09Z</time>
		</trkpt>
		<trkpt lat="50.018541" lon="13.099077">
			<ele>584.53</ele>
			<time>2024-06-23T08:28:28Z</time>
		</trkpt>
		<trkpt lat="50.018895" lon="13.099038">
			<ele>583.89</ele>
			<time>2024-06-23T08:29:00Z</time>
		</trkpt>
		<trkpt lat="50.019027" lon="13.099326">
			<ele>583.92</ele>
			<time>2024-06-23T08:30:11Z</time>
		</trkpt>
		<trkpt lat="50.018964" lon="13.099839">
			<ele>583.14</ele>
			<time>2024-06-23T08:30:40Z</time>
		</trkpt>
		<trkpt lat="50.018864" lon="13.100240">
			<ele>582.60</ele>
			<time>2024-06-23T08:31:01Z</time>
		</trkpt>
		<trkpt lat="50.018791" lon="13.100656">
			<ele>582.63</ele>
			<time>2024-06-23T08:31:27Z</time>
		</trkpt>
		<trkpt lat="50.018740" lon="13.101080">
			<ele>582.67</ele>
			<time>2024-06-23T08:31:53Z</time>
		</trkpt>
		<trkpt lat="50.018756" lon="13.101505">
			<ele>582.81</ele>
			<time>2024-06-23T08:32:16Z</time>
		</trkpt>
		<trkpt lat="50.018714" lon="13.101941">
			<ele>583.07</ele>
			<time>2024-06-23T08:32:37Z</time>
		</trkpt>
		<trkpt lat="50.018798" lon="13.102496">
			<ele>583.33</ele>
			<time>2024-06-23T08:33:50Z</time>
		</trkpt>
		<trkpt lat="50.018863" lon="13.102924">
			<ele>583.84</ele>
			<time>2024-06-23T08:34:11Z</time>
		</trkpt>
		<trkpt lat="50.018973" lon="13.103390">
			<ele>584.34</ele>
			<time>2024-06-23T08:34:53Z</time>
		</trkpt>
		<trkpt lat="50.019080" lon="13.103793">
			<ele>584.96</ele>
			<time>2024-06-23T08:35:13Z</time>
		</trkpt>
		<trkpt lat="50.019180" lon="13.104191">
			<ele>585.52</ele>
			<time>2024-06-23T08:35:34Z</time>
		</trkpt>
		<trkpt lat="50.019298" lon="13.104583">
			<ele>586.04</ele>
			<time>2024-06-23T08:35:54Z</time>
		</trkpt>
		<trkpt lat="50.019387" lon="13.104989">
			<ele>587.05</ele>
			<time>2024-06-23T08:36:16Z</time>
		</trkpt>
		<trkpt lat="50.019408" lon="13.105411">
			<ele>588.43</ele>
			<time>2024-06-23T08:36:38Z</time>
		</trkpt>
		<trkpt lat="50.019538" lon="13.105780">
			<ele>589.60</ele>
			<time>2024-06-23T08:37:20Z</time>
		</trkpt>
		<trkpt lat="50.019642" lon="13.106330">
			<ele>589.84</ele>
			<time>2024-06-23T08:38:08Z</time>
		</trkpt>
		<trkpt lat="50.019563" lon="13.106802">
			<ele>589.76</ele>
			<time>2024-06-23T08:38:58Z</time>
		</trkpt>
		<trkpt lat="50.019570" lon="13.107365">
			<ele>589.56</ele>
			<time>2024-06-23T08:39:31Z</time>
		</trkpt>
		<trkpt lat="50.019610" lon="13.107934">
			<ele>589.40</ele>
			<time>2024-06-23T08:39:56Z</time>
		</trkpt>
		<trkpt lat="50.019639" lon="13.108362">
			<ele>589.41</ele>
			<time>2024-06-23T08:40:15Z</time>
		</trkpt>
		<trkpt lat="50.019700" lon="13.108780">
			<ele>589.26</ele>
			<time>2024-06-23T08:41:01Z</time>
		</trkpt>
		<trkpt lat="50.019794" lon="13.109113">
			<ele>588.90</ele>
			<time>2024-06-23T08:41:21Z</time>
		</trkpt>
		<trkpt lat="50.019938" lon="13.109639">
			<ele>588.15</ele>
			<time>2024-06-23T08:41:53Z</time>
		</trkpt>
		<trkpt lat="50.020135" lon="13.110113">
			<ele>587.31</ele>
			<time>2024-06-23T08:42:49Z</time>
		</trkpt>
		<trkpt lat="50.020480" lon="13.110073">
			<ele>586.96</ele>
			<time>2024-06-23T08:45:03Z</time>
		</trkpt>
		<trkpt lat="50.020733" lon="13.109982">
			<ele>586.20</ele>
			<time>2024-06-23T08:46:04Z</time>
		</trkpt>
		<trkpt lat="50.020613" lon="13.110412">
			<ele>586.47</ele>
			<time>2024-06-23T08:47:41Z</time>
		</trkpt>
		<trkpt lat="50.020227" lon="13.110481">
			<ele>587.22</ele>
			<time>2024-06-23T08:50:01Z</time>
		</trkpt>
		<trkpt lat="50.020320" lon="13.111035">
			<ele>587.15</ele>
			<time>2024-06-23T08:50:44Z</time>
		</trkpt>
		<trkpt lat="50.020417" lon="13.111382">
			<ele>586.81</ele>
			<time>2024-06-23T08:51:03Z</time>
		</trkpt>
		<trkpt lat="50.020515" lon="13.111932">
			<ele>587.13</ele>
			<time>2024-06-23T08:51:43Z</time>
		</trkpt>
		<trkpt lat="50.020581" lon="13.112270">
			<ele>587.48</ele>
			<time>2024-06-23T08:52:03Z</time>
		</trkpt>
		<trkpt lat="50.020619" lon="13.112703">
			<ele>586.86</ele>
			<time>2024-06-23T08:52:26Z</time>
		</trkpt>
		<trkpt lat="50.020653" lon="13.113139">
			<ele>586.53</ele>
			<time>2024-06-23T08:52:56Z</time>
		</trkpt>
		<trkpt lat="50.020636" lon="13.113663">
			<ele>586.50</ele>
			<time>2024-06-23T08:53:31Z</time>
		</trkpt>
		<trkpt lat="50.020680" lon="13.114087">
			<ele>586.03</ele>
			<time>2024-06-23T08:53:54Z</time>
		</trkpt>
		<trkpt lat="50.020646" lon="13.114513">
			<ele>586.01</ele>
			<time>2024-06-23T08:54:16Z</time>
		</trkpt>
		<trkpt lat="50.020619" lon="13.114951">
			<ele>586.05</ele>
			<time>2024-06-23T08:54:35Z</time>
		</trkpt>
		<trkpt lat="50.020602" lon="13.115388">
			<ele>586.05</ele>
			<time>2024-06-23T08:54:54Z</time>
		</trkpt>
		<trkpt lat="50.020565" lon="13.115816">
			<ele>586.24</ele>
			<time>2024-06-23T08:55:15Z</time>
		</trkpt>
		<trkpt lat="50.020546" lon="13.116315">
			<ele>586.15</ele>
			<time>2024-06-23T08:56:12Z</time>
		</trkpt>
		<trkpt lat="50.020515" lon="13.116744">
			<ele>585.88</ele>
			<time>2024-06-23T08:56:38Z</time>
		</trkpt>
		<trkpt lat="50.020509" lon="13.117170">
			<ele>586.44</ele>
			<time>2024-06-23T08:56:59Z</time>
		</trkpt>
		<trkpt lat="50.020456" lon="13.117602">
			<ele>587.69</ele>
			<time>2024-06-23T08:57:21Z</time>
		</trkpt>
		<trkpt lat="50.020392" lon="13.118034">
			<ele>587.73</ele>
			<time>2024-06-23T08:57:41Z</time>
		</trkpt>
		<trkpt lat="50.020406" lon="13.118474">
			<ele>587.83</ele>
			<time>2024-06-23T08:58:01Z</time>
		</trkpt>
		<trkpt lat="50.020372" lon="13.118907">
			<ele>587.97</ele>
			<time>2024-06-23T08:58:24Z</time>
		</trkpt>
		<trkpt lat="50.020383" lon="13.119354">
			<ele>588.67</ele>
			<time>2024-06-23T08:58:45Z</time>
		</trkpt>
		<trkpt lat="50.020379" lon="13.119823">
			<ele>589.46</ele>
			<time>2024-06-23T08:59:12Z</time>
		</trkpt>
		<trkpt lat="50.020383" lon="13.120280">
			<ele>589.67</ele>
			<time>2024-06-23T09:01:53Z</time>
		</trkpt>
		<trkpt lat="50.020390" lon="13.120669">
			<ele>589.86</ele>
			<time>2024-06-23T09:02:32Z</time>
		</trkpt>
		<trkpt lat="50.020457" lon="13.121012">
			<ele>589.36</ele>
			<time>2024-06-23T09:03:02Z</time>
		</trkpt>
		<trkpt lat="50.020479" lon="13.121372">
			<ele>589.04</ele>
			<time>2024-06-23T09:03:21Z</time>
		</trkpt>
		<trkpt lat="50.020462" lon="13.121887">
			<ele>588.98</ele>
			<time>2024-06-23T09:06:31Z</time>
		</trkpt>
		<trkpt lat="50.020437" lon="13.122367">
			<ele>589.24</ele>
			<time>2024-06-23T09:06:59Z</time>
		</trkpt>
		<trkpt lat="50.020448" lon="13.122783">
			<ele>589.47</ele>
			<time>2024-06-23T09:07:25Z</time>
		</trkpt>
		<trkpt lat="50.020453" lon="13.123208">
			<ele>589.62</ele>
			<time>2024-06-23T09:07:48Z</time>
		</trkpt>
		<trkpt lat="50.020530" lon="13.123624">
			<ele>589.55</ele>
			<time>2024-06-23T09:08:10Z</time>
		</trkpt>
		<trkpt lat="50.020516" lon="13.124054">
			<ele>589.55</ele>
			<time>2024-06-23T09:08:31Z</time>
		</trkpt>
		<trkpt lat="50.020478" lon="13.124482">
			<ele>589.65</ele>
			<time>2024-06-23T09:08:51Z</time>
		</trkpt>
		<trkpt lat="50.020496" lon="13.124912">
			<ele>589.32</ele>
			<time>2024-06-23T09:09:17Z</time>
		</trkpt>
		<trkpt lat="50.020544" lon="13.125304">
			<ele>589.01</ele>
			<time>2024-06-23T09:09:37Z</time>
		</trkpt>
		<trkpt lat="50.020612" lon="13.125728">
			<ele>588.66</ele>
			<time>2024-06-23T09:09:57Z</time>
		</trkpt>
		<trkpt lat="50.020728" lon="13.126142">
			<ele>588.36</ele>
			<time>2024-06-23T09:10:17Z</time>
		</trkpt>
		<trkpt lat="50.020854" lon="13.126535">
			<ele>588.16</ele>
			<time>2024-06-23T09:10:36Z</time>
		</trkpt>
		<trkpt lat="50.020914" lon="13.126950">
			<ele>588.14</ele>
			<time>2024-06-23T09:10:57Z</time>
		</trkpt>
		<trkpt lat="50.020983" lon="13.127372">
			<ele>588.18</ele>
			<time>2024-06-23T09:11:17Z</time>
		</trkpt>
		<trkpt lat="50.021024" lon="13.127795">
			<ele>588.29</ele>
			<time>2024-06-23T09:11:45Z</time>
		</trkpt>
		<trkpt lat="50.021044" lon="13.128218">
			<ele>588.14</ele>
			<time>2024-06-23T09:12:20Z</time>
		</trkpt>
		<trkpt lat="50.021039" lon="13.128678">
			<ele>588.50</ele>
			<time>2024-06-23T09:13:27Z</time>
		</trkpt>
		<trkpt lat="50.021098" lon="13.129078">
			<ele>588.96</ele>
			<time>2024-06-23T09:13:56Z</time>
		</trkpt>
		<trkpt lat="50.021183" lon="13.129593">
			<ele>589.77</ele>
			<time>2024-06-23T09:14:27Z</time>
		</trkpt>
		<trkpt lat="50.021280" lon="13.130195">
			<ele>590.98</ele>
			<time>2024-06-23T09:14:57Z</time>
		</trkpt>
		<trkpt lat="50.021306" lon="13.130632">
			<ele>592.11</ele>
			<time>2024-06-23T09:15:20Z</time>
		</trkpt>
		<trkpt lat="50.021367" lon="13.131048">
			<ele>593.08</ele>
			<time>2024-06-23T09:15:43Z</time>
		</trkpt>
		<trkpt lat="50.021397" lon="13.131484">
			<ele>594.16</ele>
			<time>2024-06-23T09:16:07Z</time>
		</trkpt>
		<trkpt lat="50.021457" lon="13.131916">
			<ele>595.27</ele>
			<time>2024-06-23T09:16:30Z</time>
		</trkpt>
		<trkpt lat="50.021502" lon="13.132342">
			<ele>596.27</ele>
			<time>2024-06-23T09:16:51Z</time>
		</trkpt>
		<trkpt lat="50.021598" lon="13.132757">
			<ele>597.41</ele>
			<time>2024-06-23T09:17:13Z</time>
		</trkpt>
		<trkpt lat="50.021704" lon="13.133151">
			<ele>598.43</ele>
			<time>2024-06-23T09:17:53Z</time>
		</trkpt>
		<trkpt lat="50.021781" lon="13.133561">
			<ele>599.53</ele>
			<time>2024-06-23T09:18:17Z</time>
		</trkpt>
		<trkpt lat="50.021836" lon="13.133977">
			<ele>600.80</ele>
			<time>2024-06-23T09:18:45Z</time>
		</trkpt>
		<trkpt lat="50.021952" lon="13.134370">
			<ele>602.17</ele>
			<time>2024-06-23T09:19:11Z</time>
		</trkpt>
		<trkpt lat="50.022066" lon="13.134756">
			<ele>603.73</ele>
			<time>2024-06-23T09:19:35Z</time>
		</trkpt>
		<trkpt lat="50.022203" lon="13.135120">
			<ele>605.80</ele>
			<time>2024-06-23T09:20:00Z</time>
		</trkpt>
		<trkpt lat="50.022377" lon="13.135621">
			<ele>608.56</ele>
			<time>2024-06-23T09:20:30Z</time>
		</trkpt>
		<trkpt lat="50.022477" lon="13.136021">
			<ele>611.17</ele>
			<time>2024-06-23T09:20:51Z</time>
		</trkpt>
		<trkpt lat="50.022621" lon="13.136390">
			<ele>615.07</ele>
			<time>2024-06-23T09:21:16Z</time>
		</trkpt>
		<trkpt lat="50.022729" lon="13.136787">
			<ele>618.34</ele>
			<time>2024-06-23T09:21:37Z</time>
		</trkpt>
		<trkpt lat="50.022865" lon="13.137159">
			<ele>620.55</ele>
			<time>2024-06-23T09:22:05Z</time>
		</trkpt>
		<trkpt lat="50.023031" lon="13.137675">
			<ele>621.53</ele>
			<time>2024-06-23T09:28:10Z</time>
		</trkpt>
		<trkpt lat="50.023289" lon="13.137841">
			<ele>620.67</ele>
			<time>2024-06-23T09:28:35Z</time>
		</trkpt>
		<trkpt lat="50.023560" lon="13.137764">
			<ele>621.20</ele>
			<time>2024-06-23T09:28:59Z</time>
		</trkpt>
		<trkpt lat="50.023763" lon="13.137495">
			<ele>622.50</ele>
			<time>2024-06-23T09:29:21Z</time>
		</trkpt>
		<trkpt lat="50.023963" lon="13.137196">
			<ele>624.89</ele>
			<time>2024-06-23T09:29:46Z</time>
		</trkpt>
		<trkpt lat="50.024264" lon="13.137153">
			<ele>635.55</ele>
			<time>2024-06-23T09:30:42Z</time>
		</trkpt>
		<trkpt lat="50.024524" lon="13.137210">
			<ele>648.05</ele>
			<time>2024-06-23T09:32:51Z</time>
		</trkpt>
		<trkpt lat="50.024795" lon="13.137476">
			<ele>658.86</ele>
			<time>2024-06-23T09:34:39Z</time>
		</trkpt>
		<trkpt lat="50.025036" lon="13.137468">
			<ele>669.76</ele>
			<time>2024-06-23T09:36:11Z</time>
		</trkpt>
		<trkpt lat="50.025265" lon="13.137307">
			<ele>671.21</ele>
			<time>2024-06-23T09:43:27Z</time>
		</trkpt>
		<trkpt lat="50.025525" lon="13.137541">
			<ele>664.06</ele>
			<time>2024-06-23T09:45:18Z</time>
		</trkpt>
		<trkpt lat="50.025668" lon="13.137237">
			<ele>658.11</ele>
			<time>2024-06-23T09:46:02Z</time>
		</trkpt>
		<trkpt lat="50.025619" lon="13.136675">
			<ele>654.01</ele>
			<time>2024-06-23T09:46:34Z</time>
		</trkpt>
		<trkpt lat="50.025432" lon="13.136184">
			<ele>648.59</ele>
			<time>2024-06-23T09:47:33Z</time>
		</trkpt>
		<trkpt lat="50.025306" lon="13.135651">
			<ele>638.89</ele>
			<time>2024-06-23T09:48:14Z</time>
		</trkpt>
		<trkpt lat="50.025219" lon="13.135091">
			<ele>629.52</ele>
			<time>2024-06-23T09:49:51Z</time>
		</trkpt>
		<trkpt lat="50.025085" lon="13.134568">
			<ele>620.78</ele>
			<time>2024-06-23T09:50:27Z</time>
		</trkpt>
		<trkpt lat="50.024954" lon="13.134041">
			<ele>612.80</ele>
			<time>2024-06-23T09:51:01Z</time>
		</trkpt>
		<trkpt lat="50.024602" lon="13.134098">
			<ele>611.87</ele>
			<time>2024-06-23T09:52:09Z</time>
		</trkpt>
		<trkpt lat="50.024351" lon="13.134362">
			<ele>612.78</ele>
			<time>2024-06-23T09:52:41Z</time>
		</trkpt>
		<trkpt lat="50.024203" lon="13.134716">
			<ele>614.52</ele>
			<time>2024-06-23T09:53:05Z</time>
		</trkpt>
		<trkpt lat="50.024136" lon="13.135130">
			<ele>616.63</ele>
			<time>2024-06-23T09:53:30Z</time>
		</trkpt>
		<trkpt lat="50.024394" lon="13.135149">
			<ele>621.35</ele>
			<time>2024-06-23T09:55:28Z</time>
		</trkpt>
		<trkpt lat="50.024663" lon="13.135176">
			<ele>620.58</ele>
			<time>2024-06-23T09:55:58Z</time>
		</trkpt>
		<trkpt lat="50.024302" lon="13.135252">
			<ele>621.35</ele>
			<time>2024-06-23T10:00:34Z</time>
		</trkpt>
		<trkpt lat="50.024132" lon="13.135613">
			<ele>621.91</ele>
			<time>2024-06-23T10:00:59Z</time>
		</trkpt>
		<trkpt lat="50.023991" lon="13.135967">
			<ele>621.83</ele>
			<time>2024-06-23T10:01:19Z</time>
		</trkpt>
		<trkpt lat="50.023869" lon="13.136498">
			<ele>621.86</ele>
			<time>2024-06-23T10:01:48Z</time>
		</trkpt>
		<trkpt lat="50.023893" lon="13.136943">
			<ele>622.93</ele>
			<time>2024-06-23T10:02:12Z</time>
		</trkpt>
		<trkpt lat="50.023815" lon="13.137331">
			<ele>622.54</ele>
			<time>2024-06-23T10:02:38Z</time>
		</trkpt>
		<trkpt lat="50.023659" lon="13.137733">
			<ele>621.82</ele>
			<time>2024-06-23T10:03:15Z</time>
		</trkpt>
		<trkpt lat="50.023307" lon="13.137873">
			<ele>620.70</ele>
			<time>2024-06-23T10:03:45Z</time>
		</trkpt>
		<trkpt lat="50.023045" lon="13.137770">
			<ele>621.49</ele>
			<time>2024-06-23T10:04:10Z</time>
		</trkpt>
		<trkpt lat="50.023159" lon="13.138157">
			<ele>621.61</ele>
			<time>2024-06-23T10:49:58Z</time>
		</trkpt>
		<trkpt lat="50.023339" lon="13.138658">
			<ele>623.63</ele>
			<time>2024-06-23T10:50:34Z</time>
		</trkpt>
		<trkpt lat="50.023512" lon="13.139144">
			<ele>623.80</ele>
			<time>2024-06-23T10:51:01Z</time>
		</trkpt>
		<trkpt lat="50.023673" lon="13.139482">
			<ele>623.02</ele>
			<time>2024-06-23T10:51:21Z</time>
		</trkpt>
		<trkpt lat="50.023877" lon="13.139777">
			<ele>622.61</ele>
			<time>2024-06-23T10:51:41Z</time>
		</trkpt>
		<trkpt lat="50.024050" lon="13.140118">
			<ele>622.33</ele>
			<time>2024-06-23T10:52:01Z</time>
		</trkpt>
		<trkpt lat="50.024203" lon="13.140472">
			<ele>622.55</ele>
			<time>2024-06-23T10:52:23Z</time>
		</trkpt>
		<trkpt lat="50.024311" lon="13.140865">
			<ele>622.15</ele>
			<time>2024-06-23T10:52:47Z</time>
		</trkpt>
		<trkpt lat="50.024358" lon="13.141283">
			<ele>621.13</ele>
			<time>2024-06-23T10:53:09Z</time>
		</trkpt>
		<trkpt lat="50.024437" lon="13.141700">
			<ele>619.94</ele>
			<time>2024-06-23T10:54:59Z</time>
		</trkpt>
		<trkpt lat="50.024509" lon="13.142059">
			<ele>618.56</ele>
			<time>2024-06-23T10:57:11Z</time>
		</trkpt>
		<trkpt lat="50.024586" lon="13.142441">
			<ele>617.15</ele>
			<time>2024-06-23T10:57:38Z</time>
		</trkpt>
		<trkpt lat="50.024675" lon="13.142981">
			<ele>615.51</ele>
			<time>2024-06-23T10:58:05Z</time>
		</trkpt>
		<trkpt lat="50.024781" lon="13.143534">
			<ele>614.03</ele>
			<time>2024-06-23T10:59:01Z</time>
		</trkpt>
		<trkpt lat="50.024872" lon="13.144086">
			<ele>613.09</ele>
			<time>2024-06-23T11:00:00Z</time>
		</trkpt>
		<trkpt lat="50.024960" lon="13.144628">
			<ele>612.11</ele>
			<time>2024-06-23T11:00:39Z</time>
		</trkpt>
		<trkpt lat="50.025040" lon="13.145177">
			<ele>611.51</ele>
			<time>2024-06-23T11:01:20Z</time>
		</trkpt>
		<trkpt lat="50.025104" lon="13.145525">
			<ele>611.17</ele>
			<time>2024-06-23T11:01:59Z</time>
		</trkpt>
		<trkpt lat="50.025165" lon="13.146064">
			<ele>610.85</ele>
			<time>2024-06-23T11:02:34Z</time>
		</trkpt>
		<trkpt lat="50.025168" lon="13.146634">
			<ele>609.88</ele>
			<time>2024-06-23T11:03:07Z</time>
		</trkpt>
		<trkpt lat="50.025180" lon="13.147202">
			<ele>608.92</ele>
			<time>2024-06-23T11:03:32Z</time>
		</trkpt>
		<trkpt lat="50.025194" lon="13.147773">
			<ele>608.04</ele>
			<time>2024-06-23T11:04:02Z</time>
		</trkpt>
		<trkpt lat="50.025254" lon="13.148384">
			<ele>607.37</ele>
			<time>2024-06-23T11:04:36Z</time>
		</trkpt>
		<trkpt lat="50.025301" lon="13.148919">
			<ele>606.46</ele>
			<time>2024-06-23T11:05:42Z</time>
		</trkpt>
		<trkpt lat="50.025273" lon="13.149489">
			<ele>604.85</ele>
			<time>2024-06-23T11:06:21Z</time>
		</trkpt>
		<trkpt lat="50.025339" lon="13.150047">
			<ele>602.62</ele>
			<time>2024-06-23T11:06:49Z</time>
		</trkpt>
		<trkpt lat="50.025396" lon="13.150617">
			<ele>599.88</ele>
			<time>2024-06-23T11:07:18Z</time>
		</trkpt>
		<trkpt lat="50.025551" lon="13.151123">
			<ele>598.22</ele>
			<time>2024-06-23T11:07:43Z</time>
		</trkpt>
		<trkpt lat="50.025760" lon="13.151583">
			<ele>596.65</ele>
			<time>2024-06-23T11:08:08Z</time>
		</trkpt>
		<trkpt lat="50.026006" lon="13.152031">
			<ele>595.39</ele>
			<time>2024-06-23T11:08:43Z</time>
		</trkpt>
		<trkpt lat="50.026165" lon="13.152642">
			<ele>593.20</ele>
			<time>2024-06-23T11:09:27Z</time>
		</trkpt>
		<trkpt lat="50.026223" lon="13.153200">
			<ele>591.21</ele>
			<time>2024-06-23T11:09:59Z</time>
		</trkpt>
		<trkpt lat="50.026235" lon="13.153736">
			<ele>588.90</ele>
			<time>2024-06-23T11:10:29Z</time>
		</trkpt>
		<trkpt lat="50.026244" lon="13.154311">
			<ele>585.91</ele>
			<time>2024-06-23T11:11:04Z</time>
		</trkpt>
		<trkpt lat="50.026215" lon="13.154724">
			<ele>583.32</ele>
			<time>2024-06-23T11:11:21Z</time>
		</trkpt>
		<trkpt lat="50.025992" lon="13.155196">
			<ele>579.22</ele>
			<time>2024-06-23T11:12:18Z</time>
		</trkpt>
		<trkpt lat="50.025701" lon="13.155500">
			<ele>574.25</ele>
			<time>2024-06-23T11:13:00Z</time>
		</trkpt>
		<trkpt lat="50.025345" lon="13.155537">
			<ele>568.88</ele>
			<time>2024-06-23T11:16:23Z</time>
		</trkpt>
		<trkpt lat="50.025109" lon="13.155357">
			<ele>568.07</ele>
			<time>2024-06-23T11:17:11Z</time>
		</trkpt>
		<trkpt lat="50.024707" lon="13.155032">
			<ele>567.01</ele>
			<time>2024-06-23T11:18:48Z</time>
		</trkpt>
		<trkpt lat="50.024356" lon="13.154879">
			<ele>566.01</ele>
			<time>2024-06-23T11:19:53Z</time>
		</trkpt>
		<trkpt lat="50.024123" lon="13.154695">
			<ele>561.49</ele>
			<time>2024-06-23T11:21:44.53Z</time>
		</trkpt>
		<trkpt lat="50.023860" lon="13.154798">
			<ele>559.79</ele>
			<time>2024-06-23T11:24:39.60Z</time>
		</trkpt>
		<trkpt lat="50.023631" lon="13.154988">
			<ele>556.56</ele>
			<time>2024-06-23T11:26:54Z</time>
		</trkpt>
		<trkpt lat="50.023377" lon="13.155380">
			<ele>558.85</ele>
			<time>2024-06-23T11:29:32Z</time>
		</trkpt>
		<trkpt lat="50.023065" lon="13.155523">
			<ele>555.58</ele>
			<time>2024-06-23T11:29:58Z</time>
		</trkpt>
		<trkpt lat="50.022890" lon="13.156021">
			<ele>553.25</ele>
			<time>2024-06-23T11:30:36Z</time>
		</trkpt>
		<trkpt lat="50.022658" lon="13.156470">
			<ele>550.08</ele>
			<time>2024-06-23T11:31:11Z</time>
		</trkpt>
		<trkpt lat="50.022689" lon="13.157051">
			<ele>554.91</ele>
			<time>2024-06-23T11:31:43Z</time>
		</trkpt>
		<trkpt lat="50.022415" lon="13.157430">
			<ele>554.76</ele>
			<time>2024-06-23T11:32:33Z</time>
		</trkpt>
		<trkpt lat="50.022126" lon="13.157796">
			<ele>554.72</ele>
			<time>2024-06-23T11:33:08Z</time>
		</trkpt>
		<trkpt lat="50.021826" lon="13.158142">
			<ele>555.17</ele>
			<time>2024-06-23T11:33:36Z</time>
		</trkpt>
		<trkpt lat="50.021470" lon="13.158290">
			<ele>557.32</ele>
			<time>2024-06-23T11:34:58Z</time>
		</trkpt>
		<trkpt lat="50.021132" lon="13.158520">
			<ele>557.96</ele>
			<time>2024-06-23T11:35:40Z</time>
		</trkpt>
		<trkpt lat="50.020789" lon="13.158608">
			<ele>555.91</ele>
			<time>2024-06-23T11:36:52Z</time>
		</trkpt>
		<trkpt lat="50.020423" lon="13.158575">
			<ele>554.42</ele>
			<time>2024-06-23T11:37:33Z</time>
		</trkpt>
		<trkpt lat="50.020055" lon="13.158664">
			<ele>552.66</ele>
			<time>2024-06-23T11:38:06Z</time>
		</trkpt>
		<trkpt lat="50.019708" lon="13.158885">
			<ele>550.51</ele>
			<time>2024-06-23T11:38:40Z</time>
		</trkpt>
		<trkpt lat="50.019369" lon="13.159109">
			<ele>546.70</ele>
			<time>2024-06-23T11:39:12Z</time>
		</trkpt>
		<trkpt lat="50.019134" lon="13.159517">
			<ele>546.31</ele>
			<time>2024-06-23T11:40:41Z</time>
		</trkpt>
		<trkpt lat="50.018801" lon="13.159785">
			<ele>542.29</ele>
			<time>2024-06-23T11:41:10Z</time>
		</trkpt>
		<trkpt lat="50.018693" lon="13.160142">
			<ele>539.99</ele>
			<time>2024-06-23T11:41:39Z</time>
		</trkpt>
		<trkpt lat="50.018534" lon="13.160664">
			<ele>536.38</ele>
			<time>2024-06-23T11:42:23Z</time>
		</trkpt>
		<trkpt lat="50.018504" lon="13.161232">
			<ele>536.20</ele>
			<time>2024-06-23T11:42:55Z</time>
		</trkpt>
		<trkpt lat="50.018356" lon="13.161689">
			<ele>535.80</ele>
			<time>2024-06-23T11:43:38Z</time>
		</trkpt>
		<trkpt lat="50.018186" lon="13.162198">
			<ele>538.07</ele>
			<time>2024-06-23T11:44:12Z</time>
		</trkpt>
		<trkpt lat="50.017871" lon="13.162208">
			<ele>537.83</ele>
			<time>2024-06-23T11:45:49Z</time>
		</trkpt>
		<trkpt lat="50.017644" lon="13.161775">
			<ele>534.43</ele>
			<time>2024-06-23T11:46:29Z</time>
		</trkpt>
		<trkpt lat="50.017545" lon="13.161240">
			<ele>529.19</ele>
			<time>2024-06-23T11:46:59Z</time>
		</trkpt>
		<trkpt lat="50.017364" lon="13.160823">
			<ele>524.70</ele>
			<time>2024-06-23T11:47:25Z</time>
		</trkpt>
		<trkpt lat="50.017121" lon="13.160507">
			<ele>521.30</ele>
			<time>2024-06-23T11:48:04Z</time>
		</trkpt>
		<trkpt lat="50.016764" lon="13.160429">
			<ele>518.72</ele>
			<time>2024-06-23T11:48:43Z</time>
		</trkpt>
		<trkpt lat="50.016406" lon="13.160320">
			<ele>515.31</ele>
			<time>2024-06-23T11:49:20Z</time>
		</trkpt>
		<trkpt lat="50.016442" lon="13.160874">
			<ele>522.41</ele>
			<time>2024-06-23T11:52:08Z</time>
		</trkpt>
		<trkpt lat="50.016375" lon="13.160272">
			<ele>513.86</ele>
			<time>2024-06-23T11:54:47Z</time>
		</trkpt>
		<trkpt lat="50.016230" lon="13.159865">
			<ele>509.27</ele>
			<time>2024-06-23T11:56:09Z</time>
		</trkpt>
		<trkpt lat="50.016290" lon="13.159382">
			<ele>505.65</ele>
			<time>2024-06-23T11:56:37Z</time>
		</trkpt>
		<trkpt lat="50.015940" lon="13.159345">
			<ele>502.89</ele>
			<time>2024-06-23T11:57:18Z</time>
		</trkpt>
		<trkpt lat="50.015638" lon="13.159558">
			<ele>500.58</ele>
			<time>2024-06-23T12:04:41Z</time>
		</trkpt>
		<trkpt lat="50.015328" lon="13.159864">
			<ele>498.19</ele>
			<time>2024-06-23T12:05:09Z</time>
		</trkpt>
		<trkpt lat="50.015028" lon="13.160179">
			<ele>496.91</ele>
			<time>2024-06-23T12:05:39Z</time>
		</trkpt>
		<trkpt lat="50.014685" lon="13.160299">
			<ele>494.94</ele>
			<time>2024-06-23T12:06:09Z</time>
		</trkpt>
		<trkpt lat="50.014348" lon="13.160080">
			<ele>492.99</ele>
			<time>2024-06-23T12:06:39Z</time>
		</trkpt>
		<trkpt lat="50.014080" lon="13.160004">
			<ele>491.87</ele>
			<time>2024-06-23T12:07:02Z</time>
		</trkpt>
		<trkpt lat="50.013853" lon="13.160076">
			<ele>491.41</ele>
			<time>2024-06-23T12:07:21Z</time>
		</trkpt>
		<trkpt lat="50.013593" lon="13.160216">
			<ele>491.21</ele>
			<time>2024-06-23T12:07:41Z</time>
		</trkpt>
		<trkpt lat="50.013366" lon="13.160456">
			<ele>490.14</ele>
			<time>2024-06-23T12:08:11Z</time>
		</trkpt>
		<trkpt lat="50.013171" lon="13.160929">
			<ele>488.54</ele>
			<time>2024-06-23T12:08:40Z</time>
		</trkpt>
		<trkpt lat="50.012976" lon="13.161335">
			<ele>487.24</ele>
			<time>2024-06-23T12:09:07Z</time>
		</trkpt>
		<trkpt lat="50.012731" lon="13.161612">
			<ele>486.35</ele>
			<time>2024-06-23T12:09:32Z</time>
		</trkpt>
		<trkpt lat="50.012524" lon="13.161899">
			<ele>485.70</ele>
			<time>2024-06-23T12:09:55Z</time>
		</trkpt>
		<trkpt lat="50.012233" lon="13.162234">
			<ele>484.76</ele>
			<time>2024-06-23T12:12:02Z</time>
		</trkpt>
		<trkpt lat="50.011896" lon="13.162454">
			<ele>483.75</ele>
			<time>2024-06-23T12:12:31Z</time>
		</trkpt>
		<trkpt lat="50.011651" lon="13.162654">
			<ele>483.12</ele>
			<time>2024-06-23T12:12:51Z</time>
		</trkpt>
		<trkpt lat="50.011400" lon="13.162864">
			<ele>482.58</ele>
			<time>2024-06-23T12:13:13Z</time>
		</trkpt>
		<trkpt lat="50.011160" lon="13.163078">
			<ele>481.96</ele>
			<time>2024-06-23T12:13:33Z</time>
		</trkpt>
		<trkpt lat="50.010929" lon="13.163251">
			<ele>481.58</ele>
			<time>2024-06-23T12:13:54Z</time>
		</trkpt>
		<trkpt lat="50.010611" lon="13.163267">
			<ele>480.82</ele>
			<time>2024-06-23T12:14:19Z</time>
		</trkpt>
		<trkpt lat="50.010299" lon="13.163147">
			<ele>479.64</ele>
			<time>2024-06-23T12:14:44Z</time>
		</trkpt>
		<trkpt lat="50.009943" lon="13.162993">
			<ele>478.64</ele>
			<time>2024-06-23T12:15:10Z</time>
		</trkpt>
		<trkpt lat="50.009632" lon="13.162915">
			<ele>477.97</ele>
			<time>2024-06-23T12:15:36Z</time>
		</trkpt>
		<trkpt lat="50.009355" lon="13.162896">
			<ele>478.85</ele>
			<time>2024-06-23T12:15:59Z</time>
		</trkpt>
		<trkpt lat="50.009084" lon="13.162792">
			<ele>480.30</ele>
			<time>2024-06-23T12:16:21Z</time>
		</trkpt>
		<trkpt lat="50.008823" lon="13.162659">
			<ele>481.90</ele>
			<time>2024-06-23T12:16:41Z</time>
		</trkpt>
		<trkpt lat="50.008567" lon="13.162494">
			<ele>483.64</ele>
			<time>2024-06-23T12:17:02Z</time>
		</trkpt>
		<trkpt lat="50.008307" lon="13.162332">
			<ele>485.29</ele>
			<time>2024-06-23T12:17:26Z</time>
		</trkpt>
		<trkpt lat="50.008045" lon="13.162167">
			<ele>486.77</ele>
			<time>2024-06-23T12:17:50Z</time>
		</trkpt>
		<trkpt lat="50.007794" lon="13.161982">
			<ele>488.00</ele>
			<time>2024-06-23T12:18:12Z</time>
		</trkpt>
		<trkpt lat="50.007551" lon="13.161770">
			<ele>488.45</ele>
			<time>2024-06-23T12:18:33Z</time>
		</trkpt>
		<trkpt lat="50.007332" lon="13.161506">
			<ele>487.89</ele>
			<time>2024-06-23T12:19:13Z</time>
		</trkpt>
		<trkpt lat="50.007004" lon="13.161254">
			<ele>484.14</ele>
			<time>2024-06-23T12:19:44Z</time>
		</trkpt>
		<trkpt lat="50.006691" lon="13.160959">
			<ele>480.50</ele>
			<time>2024-06-23T12:20:16Z</time>
		</trkpt>
		<trkpt lat="50.006400" lon="13.160611">
			<ele>477.93</ele>
			<time>2024-06-23T12:20:45Z</time>
		</trkpt>
		<trkpt lat="50.006130" lon="13.160128">
			<ele>476.34</ele>
			<time>2024-06-23T12:22:00Z</time>
		</trkpt>
		<trkpt lat="50.005933" lon="13.159668">
			<ele>476.67</ele>
			<time>2024-06-23T12:22:38Z</time>
		</trkpt>
		<trkpt lat="50.005774" lon="13.159195">
			<ele>477.33</ele>
			<time>2024-06-23T12:23:14Z</time>
		</trkpt>
		<trkpt lat="50.005581" lon="13.158691">
			<ele>477.82</ele>
			<time>2024-06-23T12:24:02Z</time>
		</trkpt>
		<trkpt lat="50.005379" lon="13.158292">
			<ele>478.61</ele>
			<time>2024-06-23T12:24:45Z</time>
		</trkpt>
		<trkpt lat="50.005180" lon="13.157997">
			<ele>479.13</ele>
			<time>2024-06-23T12:25:05Z</time>
		</trkpt>
		<trkpt lat="50.004954" lon="13.157687">
			<ele>479.70</ele>
			<time>2024-06-23T12:25:29Z</time>
		</trkpt>
		<trkpt lat="50.004750" lon="13.157403">
			<ele>480.84</ele>
			<time>2024-06-23T12:25:52Z</time>
		</trkpt>
		<trkpt lat="50.004555" lon="13.157202">
			<ele>481.81</ele>
			<time>2024-06-23T12:26:18Z</time>
		</trkpt>
		<trkpt lat="50.004306" lon="13.157026">
			<ele>482.08</ele>
			<time>2024-06-23T12:26:43Z</time>
		</trkpt>
		<trkpt lat="50.003973" lon="13.156777">
			<ele>483.39</ele>
			<time>2024-06-23T12:27:17Z</time>
		</trkpt>
		<trkpt lat="50.003616" lon="13.156663">
			<ele>485.00</ele>
			<time>2024-06-23T12:27:48Z</time>
		</trkpt>
		<trkpt lat="50.003251" lon="13.156639">
			<ele>490.17</ele>
			<time>2024-06-23T12:28:27Z</time>
		</trkpt>
		<trkpt lat="50.002894" lon="13.156600">
			<ele>494.04</ele>
			<time>2024-06-23T12:29:00Z</time>
		</trkpt>
		<trkpt lat="50.002534" lon="13.156616">
			<ele>498.44</ele>
			<time>2024-06-23T12:29:35Z</time>
		</trkpt>
		<trkpt lat="50.002182" lon="13.156767">
			<ele>504.06</ele>
			<time>2024-06-23T12:30:15Z</time>
		</trkpt>
		<trkpt lat="50.001828" lon="13.156719">
			<ele>508.78</ele>
			<time>2024-06-23T12:31:01Z</time>
		</trkpt>
		<trkpt lat="50.001476" lon="13.156556">
			<ele>512.56</ele>
			<time>2024-06-23T12:31:37Z</time>
		</trkpt>
		<trkpt lat="50.001130" lon="13.156389">
			<ele>515.19</ele>
			<time>2024-06-23T12:32:35Z</time>
		</trkpt>
		<trkpt lat="50.000774" lon="13.156296">
			<ele>518.79</ele>
			<time>2024-06-23T12:33:08Z</time>
		</trkpt>
		<trkpt lat="50.000419" lon="13.156195">
			<ele>523.18</ele>
			<time>2024-06-23T12:33:55Z</time>
		</trkpt>
		<trkpt lat="50.000053" lon="13.156187">
			<ele>527.77</ele>
			<time>2024-06-23T12:35:21Z</time>
		</trkpt>
		<trkpt lat="49.999723" lon="13.155937">
			<ele>532.43</ele>
			<time>2024-06-23T12:35:58Z</time>
		</trkpt>
		<trkpt lat="49.999377" lon="13.155754">
			<ele>537.86</ele>
			<time>2024-06-23T12:36:37Z</time>
		</trkpt>
		<trkpt lat="49.999032" lon="13.155577">
			<ele>543.84</ele>
			<time>2024-06-23T12:37:14Z</time>
		</trkpt>
		<trkpt lat="49.998681" lon="13.155655">
			<ele>547.74</ele>
			<time>2024-06-23T12:38:00Z</time>
		</trkpt>
		<trkpt lat="49.998338" lon="13.155840">
			<ele>550.36</ele>
			<time>2024-06-23T12:38:33Z</time>
		</trkpt>
		<trkpt lat="49.998012" lon="13.156081">
			<ele>553.04</ele>
			<time>2024-06-23T12:39:02Z</time>
		</trkpt>
		<trkpt lat="49.997670" lon="13.156292">
			<ele>556.85</ele>
			<time>2024-06-23T12:39:34Z</time>
		</trkpt>
		<trkpt lat="49.997402" lon="13.156701">
			<ele>560.67</ele>
			<time>2024-06-23T12:40:34Z</time>
		</trkpt>
		<trkpt lat="49.997366" lon="13.157260">
			<ele>562.36</ele>
			<time>2024-06-23T12:41:15Z</time>
		</trkpt>
		<trkpt lat="49.997159" lon="13.157727">
			<ele>568.58</ele>
			<time>2024-06-23T12:54:20Z</time>
		</trkpt>
		<trkpt lat="49.997143" lon="13.158157">
			<ele>573.51</ele>
			<time>2024-06-23T12:55:02Z</time>
		</trkpt>
		<trkpt lat="49.997224" lon="13.158716">
			<ele>580.02</ele>
			<time>2024-06-23T12:55:49Z</time>
		</trkpt>
		<trkpt lat="49.997067" lon="13.159186">
			<ele>586.78</ele>
			<time>2024-06-23T12:56:46Z</time>
		</trkpt>
		<trkpt lat="49.996831" lon="13.159612">
			<ele>594.69</ele>
			<time>2024-06-23T12:58:13Z</time>
		</trkpt>
		<trkpt lat="49.996736" lon="13.159979">
			<ele>597.27</ele>
			<time>2024-06-23T12:58:51Z</time>
		</trkpt>
		<trkpt lat="49.996552" lon="13.160259">
			<ele>602.06</ele>
			<time>2024-06-23T12:59:24Z</time>
		</trkpt>
		<trkpt lat="49.996322" lon="13.160331">
			<ele>609.00</ele>
			<time>2024-06-23T13:00:11Z</time>
		</trkpt>
		<trkpt lat="49.996053" lon="13.160356">
			<ele>619.67</ele>
			<time>2024-06-23T13:01:06Z</time>
		</trkpt>
		<trkpt lat="49.995791" lon="13.160465">
			<ele>628.65</ele>
			<time>2024-06-23T13:02:27Z</time>
		</trkpt>
		<trkpt lat="49.995411" lon="13.160665">
			<ele>643.18</ele>
			<time>2024-06-23T13:04:18Z</time>
		</trkpt>
		<trkpt lat="49.995144" lon="13.161025">
			<ele>649.43</ele>
			<time>2024-06-23T13:05:25Z</time>
		</trkpt>
		<trkpt lat="49.994791" lon="13.161090">
			<ele>651.44</ele>
			<time>2024-06-23T13:06:06Z</time>
		</trkpt>
		<trkpt lat="49.994443" lon="13.161225">
			<ele>655.06</ele>
			<time>2024-06-23T13:06:52Z</time>
		</trkpt>
		<trkpt lat="49.994119" lon="13.161475">
			<ele>656.62</ele>
			<time>2024-06-23T13:07:27Z</time>
		</trkpt>
		<trkpt lat="49.993777" lon="13.161490">
			<ele>656.53</ele>
			<time>2024-06-23T13:08:05Z</time>
		</trkpt>
		<trkpt lat="49.993620" lon="13.160971">
			<ele>656.90</ele>
			<time>2024-06-23T13:08:38Z</time>
		</trkpt>
		<trkpt lat="49.993619" lon="13.160390">
			<ele>656.16</ele>
			<time>2024-06-23T13:09:09Z</time>
		</trkpt>
		<trkpt lat="49.993711" lon="13.159837">
			<ele>655.37</ele>
			<time>2024-06-23T13:09:39Z</time>
		</trkpt>
		<trkpt lat="49.993861" lon="13.159316">
			<ele>656.04</ele>
			<time>2024-06-23T13:10:12Z</time>
		</trkpt>
		<trkpt lat="49.993889" lon="13.158736">
			<ele>656.38</ele>
			<time>2024-06-23T13:10:55Z</time>
		</trkpt>
		<trkpt lat="49.993973" lon="13.158181">
			<ele>658.32</ele>
			<time>2024-06-23T13:11:27Z</time>
		</trkpt>
		<trkpt lat="49.994254" lon="13.157826">
			<ele>659.80</ele>
			<time>2024-06-23T13:13:07Z</time>
		</trkpt>
		<trkpt lat="49.994576" lon="13.157600">
			<ele>657.42</ele>
			<time>2024-06-23T13:14:57Z</time>
		</trkpt>
		<trkpt lat="49.994867" lon="13.157437">
			<ele>656.76</ele>
			<time>2024-06-23T13:17:18Z</time>
		</trkpt>
		<trkpt lat="49.995168" lon="13.157366">
			<ele>656.63</ele>
			<time>2024-06-23T13:18:46Z</time>
		</trkpt>
		<trkpt lat="49.995526" lon="13.157335">
			<ele>657.32</ele>
			<time>2024-06-23T13:21:40Z</time>
		</trkpt>
		<trkpt lat="49.995177" lon="13.157567">
			<ele>656.53</ele>
			<time>2024-06-23T13:47:23Z</time>
		</trkpt>
		<trkpt lat="49.994819" lon="13.157607">
			<ele>657.32</ele>
			<time>2024-06-23T13:48:59Z</time>
		</trkpt>
		<trkpt lat="49.994551" lon="13.157938">
			<ele>658.19</ele>
			<time>2024-06-23T13:50:26Z</time>
		</trkpt>
		<trkpt lat="49.994238" lon="13.158225">
			<ele>659.25</ele>
			<time>2024-06-23T13:51:22Z</time>
		</trkpt>
		<trkpt lat="49.993977" lon="13.158610">
			<ele>657.51</ele>
			<time>2024-06-23T13:52:00Z</time>
		</trkpt>
		<trkpt lat="49.993838" lon="13.159073">
			<ele>655.76</ele>
			<time>2024-06-23T13:52:28Z</time>
		</trkpt>
		<trkpt lat="49.993750" lon="13.159625">
			<ele>655.00</ele>
			<time>2024-06-23T13:53:09Z</time>
		</trkpt>
		<trkpt lat="49.993631" lon="13.160139">
			<ele>655.42</ele>
			<time>2024-06-23T13:55:08Z</time>
		</trkpt>
		<trkpt lat="49.993596" lon="13.160678">
			<ele>656.64</ele>
			<time>2024-06-23T13:55:56Z</time>
		</trkpt>
		<trkpt lat="49.993694" lon="13.161217">
			<ele>656.90</ele>
			<time>2024-06-23T13:56:45Z</time>
		</trkpt>
		<trkpt lat="49.993780" lon="13.161792">
			<ele>652.81</ele>
			<time>2024-06-23T13:57:37Z</time>
		</trkpt>
		<trkpt lat="49.993812" lon="13.162392">
			<ele>641.42</ele>
			<time>2024-06-23T13:58:26Z</time>
		</trkpt>
		<trkpt lat="49.993788" lon="13.162966">
			<ele>632.03</ele>
			<time>2024-06-23T13:59:21Z</time>
		</trkpt>
		<trkpt lat="49.993765" lon="13.163488">
			<ele>623.36</ele>
			<time>2024-06-23T13:59:56Z</time>
		</trkpt>
		<trkpt lat="49.993819" lon="13.164076">
			<ele>615.32</ele>
			<time>2024-06-23T14:00:38Z</time>
		</trkpt>
		<trkpt lat="49.993697" lon="13.164596">
			<ele>606.48</ele>
			<time>2024-06-23T14:01:20Z</time>
		</trkpt>
		<trkpt lat="49.993437" lon="13.164993">
			<ele>596.95</ele>
			<time>2024-06-23T14:02:57Z</time>
		</trkpt>
		<trkpt lat="49.993121" lon="13.165279">
			<ele>590.09</ele>
			<time>2024-06-23T14:03:31Z</time>
		</trkpt>
		<trkpt lat="49.992775" lon="13.165474">
			<ele>580.34</ele>
			<time>2024-06-23T14:04:04Z</time>
		</trkpt>
		<trkpt lat="49.992457" lon="13.165758">
			<ele>573.57</ele>
			<time>2024-06-23T14:04:36Z</time>
		</trkpt>
		<trkpt lat="49.992103" lon="13.165905">
			<ele>568.00</ele>
			<time>2024-06-23T14:05:28Z</time>
		</trkpt>
		<trkpt lat="49.991745" lon="13.165823">
			<ele>560.97</ele>
			<time>2024-06-23T14:06:03Z</time>
		</trkpt>
		<trkpt lat="49.991374" lon="13.165709">
			<ele>556.93</ele>
			<time>2024-06-23T14:06:41Z</time>
		</trkpt>
		<trkpt lat="49.991079" lon="13.165480">
			<ele>555.27</ele>
			<time>2024-06-23T14:07:11Z</time>
		</trkpt>
		<trkpt lat="49.990823" lon="13.165218">
			<ele>554.49</ele>
			<time>2024-06-23T14:07:35Z</time>
		</trkpt>
		<trkpt lat="49.990603" lon="13.164946">
			<ele>553.54</ele>
			<time>2024-06-23T14:07:56Z</time>
		</trkpt>
		<trkpt lat="49.990438" lon="13.164463">
			<ele>550.85</ele>
			<time>2024-06-23T14:09:26Z</time>
		</trkpt>
		<trkpt lat="49.990118" lon="13.164368">
			<ele>546.44</ele>
			<time>2024-06-23T14:10:09Z</time>
		</trkpt>
		<trkpt lat="49.989768" lon="13.164519">
			<ele>542.50</ele>
			<time>2024-06-23T14:10:47Z</time>
		</trkpt>
		<trkpt lat="49.989409" lon="13.164622">
			<ele>538.88</ele>
			<time>2024-06-23T14:11:37Z</time>
		</trkpt>
		<trkpt lat="49.989141" lon="13.164631">
			<ele>536.67</ele>
			<time>2024-06-23T14:12:07Z</time>
		</trkpt>
		<trkpt lat="49.988895" lon="13.164670">
			<ele>534.20</ele>
			<time>2024-06-23T14:12:27Z</time>
		</trkpt>
		<trkpt lat="49.988667" lon="13.164302">
			<ele>532.92</ele>
			<time>2024-06-23T14:13:00Z</time>
		</trkpt>
		<trkpt lat="49.988369" lon="13.163983">
			<ele>530.96</ele>
			<time>2024-06-23T14:16:18Z</time>
		</trkpt>
		<trkpt lat="49.988008" lon="13.164048">
			<ele>527.68</ele>
			<time>2024-06-23T14:17:14Z</time>
		</trkpt>
		<trkpt lat="49.987643" lon="13.164118">
			<ele>524.13</ele>
			<time>2024-06-23T14:18:02Z</time>
		</trkpt>
		<trkpt lat="49.987281" lon="13.164209">
			<ele>520.42</ele>
			<time>2024-06-23T14:18:45Z</time>
		</trkpt>
		<trkpt lat="49.986928" lon="13.164386">
			<ele>516.87</ele>
			<time>2024-06-23T14:20:01Z</time>
		</trkpt>
		<trkpt lat="49.986591" lon="13.164641">
			<ele>513.60</ele>
			<time>2024-06-23T14:20:58Z</time>
		</trkpt>
		<trkpt lat="49.986259" lon="13.164872">
			<ele>510.54</ele>
			<time>2024-06-23T14:21:39Z</time>
		</trkpt>
		<trkpt lat="49.985909" lon="13.165062">
			<ele>507.53</ele>
			<time>2024-06-23T14:22:32Z</time>
		</trkpt>
		<trkpt lat="49.985548" lon="13.165154">
			<ele>505.38</ele>
			<time>2024-06-23T14:23:19Z</time>
		</trkpt>
		<trkpt lat="49.985225" lon="13.164888">
			<ele>504.62</ele>
			<time>2024-06-23T14:24:05Z</time>
		</trkpt>
		<trkpt lat="49.985005" lon="13.164436">
			<ele>504.30</ele>
			<time>2024-06-23T14:24:38Z</time>
		</trkpt>
		<trkpt lat="49.984653" lon="13.164305">
			<ele>502.68</ele>
			<time>2024-06-23T14:25:10Z</time>
		</trkpt>
		<trkpt lat="49.984299" lon="13.164441">
			<ele>499.67</ele>
			<time>2024-06-23T14:25:41Z</time>
		</trkpt>
		<trkpt lat="49.983946" lon="13.164617">
			<ele>496.33</ele>
			<time>2024-06-23T14:26:13Z</time>
		</trkpt>
		<trkpt lat="49.983670" lon="13.164915">
			<ele>491.87</ele>
			<time>2024-06-23T14:27:22Z</time>
		</trkpt>
		<trkpt lat="49.983359" lon="13.165184">
			<ele>486.82</ele>
			<time>2024-06-23T14:27:53Z</time>
		</trkpt>
		<trkpt lat="49.983052" lon="13.165451">
			<ele>482.87</ele>
			<time>2024-06-23T14:28:30Z</time>
		</trkpt>
		<trkpt lat="49.982768" lon="13.165882">
			<ele>480.64</ele>
			<time>2024-06-23T14:29:05Z</time>
		</trkpt>
		<trkpt lat="49.982546" lon="13.166358">
			<ele>478.26</ele>
			<time>2024-06-23T14:30:04Z</time>
		</trkpt>
		<trkpt lat="49.982350" lon="13.166845">
			<ele>475.78</ele>
			<time>2024-06-23T14:30:39Z</time>
		</trkpt>
		<trkpt lat="49.981990" lon="13.167018">
			<ele>472.67</ele>
			<time>2024-06-23T14:31:23Z</time>
		</trkpt>
		<trkpt lat="49.981646" lon="13.167321">
			<ele>466.99</ele>
			<time>2024-06-23T14:32:07Z</time>
		</trkpt>
		<trkpt lat="49.981449" lon="13.167779">
			<ele>460.55</ele>
			<time>2024-06-23T14:33:22Z</time>
		</trkpt>
		<trkpt lat="49.981166" lon="13.168009">
			<ele>458.87</ele>
			<time>2024-06-23T14:33:55Z</time>
		</trkpt>
		<trkpt lat="49.980916" lon="13.167875">
			<ele>458.87</ele>
			<time>2024-06-23T14:34:20Z</time>
		</trkpt>
		<trkpt lat="49.980671" lon="13.167703">
			<ele>458.94</ele>
			<time>2024-06-23T14:34:46Z</time>
		</trkpt>
		<trkpt lat="49.980419" lon="13.167508">
			<ele>459.48</ele>
			<time>2024-06-23T14:35:06Z</time>
		</trkpt>
		<trkpt lat="49.980171" lon="13.167319">
			<ele>459.96</ele>
			<time>2024-06-23T14:35:24Z</time>
		</trkpt>
		<trkpt lat="49.979930" lon="13.167108">
			<ele>460.22</ele>
			<time>2024-06-23T14:35:45Z</time>
		</trkpt>
		<trkpt lat="49.979683" lon="13.166863">
			<ele>461.10</ele>
			<time>2024-06-23T14:36:05Z</time>
		</trkpt>
		<trkpt lat="49.979463" lon="13.166597">
			<ele>462.12</ele>
			<time>2024-06-23T14:36:27Z</time>
		</trkpt>
		<trkpt lat="49.979245" lon="13.166332">
			<ele>463.27</ele>
			<time>2024-06-23T14:36:50Z</time>
		</trkpt>
		<trkpt lat="49.979049" lon="13.166019">
			<ele>464.24</ele>
			<time>2024-06-23T14:37:13Z</time>
		</trkpt>
		<trkpt lat="49.978825" lon="13.165750">
			<ele>465.08</ele>
			<time>2024-06-23T14:37:36Z</time>
		</trkpt>
		<trkpt lat="49.978574" lon="13.165579">
			<ele>466.09</ele>
			<time>2024-06-23T14:37:58Z</time>
		</trkpt>
		<trkpt lat="49.978308" lon="13.165469">
			<ele>467.03</ele>
			<time>2024-06-23T14:38:18Z</time>
		</trkpt>
		<trkpt lat="49.977959" lon="13.165308">
			<ele>468.21</ele>
			<time>2024-06-23T14:38:46Z</time>
		</trkpt>
		<trkpt lat="49.977656" lon="13.165166">
			<ele>468.47</ele>
			<time>2024-06-23T14:39:11Z</time>
		</trkpt>
		<trkpt lat="49.977409" lon="13.165035">
			<ele>468.76</ele>
			<time>2024-06-23T14:39:32Z</time>
		</trkpt>
		<trkpt lat="49.977144" lon="13.164959">
			<ele>468.92</ele>
			<time>2024-06-23T14:39:53Z</time>
		</trkpt>
		<trkpt lat="49.976890" lon="13.164832">
			<ele>468.97</ele>
			<time>2024-06-23T14:40:14Z</time>
		</trkpt>
		<trkpt lat="49.976652" lon="13.164742">
			<ele>468.96</ele>
			<time>2024-06-23T14:40:33Z</time>
		</trkpt>
		<trkpt lat="49.976386" lon="13.164627">
			<ele>468.74</ele>
			<time>2024-06-23T14:40:57Z</time>
		</trkpt>
		<trkpt lat="49.976105" lon="13.164549">
			<ele>468.62</ele>
			<time>2024-06-23T14:41:19Z</time>
		</trkpt>
		<trkpt lat="49.975832" lon="13.164460">
			<ele>468.70</ele>
			<time>2024-06-23T14:41:40Z</time>
		</trkpt>
		<trkpt lat="49.975565" lon="13.164381">
			<ele>468.44</ele>
			<time>2024-06-23T14:42:03Z</time>
		</trkpt>
		<trkpt lat="49.975320" lon="13.164335">
			<ele>468.05</ele>
			<time>2024-06-23T14:42:33Z</time>
		</trkpt>
		<extensions>
			<gte:name>#1</gte:name>
			<gte:color>#fbaf00</gte:color>
		</extensions>
	</trkseg>
</trk>
</gpx>