<?xml version="1.0" encoding="UTF-8"?>
<gpx version="1.1" creator="GPS Track Editor" xmlns="http://www.topografix.com/GPX/1/1" xmlns:xsi="http://www.w3.org/2001/XMLSchema-instance" xmlns:gte="http://www.gpstrackeditor.com/xmlschemas/General/1" xmlns:gpxtpx="http://www.garmin.com/xmlschemas/TrackPointExtension/v1" xmlns:gpxx="http://www.garmin.com/xmlschemas/GpxExtensions/v3" targetNamespace="http://www.topografix.com/GPX/1/1" elementFormDefault="qualified" xsi:schemaLocation="http://www.topografix.com/GPX/1/1 http://www.topografix.com/GPX/1/1/gpx.xsd">
<metadata>
	<name>20201107 - Plzen - Plzen.gpx</name>
	<desc>20,427,-425
        </desc>
	<keywords>Monca, Kata, ja</keywords>
</metadata>
<trk>
	<name>20201107 - sobota</name>
	<desc>Color:004000ff</desc>
	<trkseg>
		<trkpt lat="49.778114" lon="13.375038">
			<ele>361.00</ele>
			<time>2020-11-07T08:54:34Z</time>
			<extensions>
				<gte:gps speed="0.0"/>
			</extensions>
		</trkpt>
		<trkpt lat="49.779842" lon="13.381563">
			<ele>337.38</ele>
			<time>2020-11-07T09:03:04Z</time>
			<extensions>
				<gte:gps speed="5.6"/>
			</extensions>
		</trkpt>
		<trkpt lat="49.780516" lon="13.388714">
			<ele>335.00</ele>
			<time>2020-11-07T09:11:02Z</time>
			<extensions>
				<gte:gps speed="5.9"/>
			</extensions>
		</trkpt>
		<trkpt lat="49.784042" lon="13.393135">
			<ele>325.00</ele>
			<time>2020-11-07T09:18:10Z</time>
			<extensions>
				<gte:gps speed="0.3"/>
			</extensions>
		</trkpt>
		<trkpt lat="49.787003" lon="13.398418">
			<ele>352.75</ele>
			<time>2020-11-07T09:27:02Z</time>
			<extensions>
				<gte:gps speed="5.2"/>
			</extensions>
		</trkpt>
		<trkpt lat="49.788883" lon="13.405337">
			<ele>381.26</ele>
			<time>2020-11-07T09:34:16Z</time>
			<extensions>
				<gte:gps speed="4.1"/>
			</extensions>
		</trkpt>
		<trkpt lat="49.791951" lon="13.410730">
			<ele>382.00</ele>
			<time>2020-11-07T09:40:23Z</time>
			<extensions>
				<gte:gps speed="4.2"/>
			</extensions>
		</trkpt>
		<trkpt lat="49.792133" lon="13.418062">
			<ele>369.83</ele>
			<time>2020-11-07T09:46:45Z</time>
			<extensions>
				<gte:gps speed="5.7"/>
			</extensions>
		</trkpt>
		<trkpt lat="49.792822" lon="13.425428">
			<ele>356.35</ele>
			<time>2020-11-07T09:52:47Z</time>
			<extensions>
				<gte:gps speed="5.4"/>
			</extensions>
		</trkpt>
		<trkpt lat="49.794258" lon="13.432361">
			<ele>354.71</ele>
			<time>2020-11-07T09:59:25Z</time>
			<extensions>
				<gte:gps speed="5.3"/>
			</extensions>
		</trkpt>
		<trkpt lat="49.794514" lon="13.439667">
			<ele>355.65</ele>
			<time>2020-11-07T10:06:51Z</time>
			<extensions>
				<gte:gps speed="5.2"/>
			</extensions>
		</trkpt>
		<trkpt lat="49.793913" lon="13.446600">
			<ele>346.00</ele>
			<time>2020-11-07T10:28:21Z</time>
			<extensions>
				<gte:gps speed="0.0"/>
			</extensions>
		</trkpt>
		<trkpt lat="49.789303" lon="13.445520">
			<ele>341.76</ele>
			<time>2020-11-07T10:34:26Z</time>
			<extensions>
				<gte:gps speed="5.2"/>
			</extensions>
		</trkpt>
		<trkpt lat="49.786728" lon="13.451259">
			<ele>330.88</ele>
			<time>2020-11-07T10:43:19Z</time>
			<extensions>
				<gte:gps speed="3.6"/>
			</extensions>
		</trkpt>
		<trkpt lat="49.783297" lon="13.446508">
			<ele>337.77</ele>
			<time>2020-11-07T11:03:29Z</time>
			<extensions>
				<gte:gps speed="0.0"/>
			</extensions>
		</trkpt>
		<trkpt lat="49.779340" lon="13.442571">
			<ele>339.00</ele>
			<time>2020-11-07T11:15:28Z</time>
			<extensions>
				<gte:gps speed="0.0"/>
			</extensions>
		</trkpt>
		<trkpt lat="49.774668" lon="13.441320">
			<ele>320.19</ele>
			<time>2020-11-07T11:24:56Z</time>
			<extensions>
				<gte:gps speed="3.2"/>
			</extensions>
		</trkpt>
		<trkpt lat="49.775961" lon="13.434455">
			<ele>308.06</ele>
			<time>2020-11-07T11:32:42Z</time>
			<extensions>
				<gte:gps speed="2.6"/>
			</extensions>
		</trkpt>
		<trkpt lat="49.780720" lon="13.433730">
			<ele>314.41</ele>
			<time>2020-11-07T11:45:24Z</time>
			<extensions>
				<gte:gps speed="4.7"/>
			</extensions>
		</trkpt>
		<trkpt lat="49.784995" lon="13.435920">
			<ele>318.45</ele>
			<time>2020-11-07T12:11:05Z</time>
			<extensions>
				<gte:gps speed="3.0"/>
			</extensions>
		</trkpt>
		<trkpt lat="49.788029" lon="13.430598">
			<ele>334.53</ele>
			<time>2020-11-07T12:23:59Z</time>
			<extensions>
				<gte:gps speed="4.8"/>
			</extensions>
		</trkpt>
		<trkpt lat="49.788106" lon="13.423421">
			<ele>349.77</ele>
			<time>2020-11-07T14:12:22Z</time>
			<extensions>
				<gte:gps speed="3.4"/>
			</extensions>
		</trkpt>
		<trkpt lat="49.783878" lon="13.419942">
			<ele>326.92</ele>
			<time>2020-11-07T14:24:43Z</time>
			<extensions>
				<gte:gps speed="5.5"/>
			</extensions>
		</trkpt>
		<trkpt lat="49.780133" lon="13.415784">
			<ele>318.31</ele>
			<time>2020-11-07T14:33:54Z</time>
			<extensions>
				<gte:gps speed="2.4"/>
			</extensions>
		</trkpt>
		<trkpt lat="49.777314" lon="13.410255">
			<ele>331.67</ele>
			<time>2020-11-07T14:41:49Z</time>
			<extensions>
				<gte:gps speed="0.0"/>
			</extensions>
		</trkpt>
		<trkpt lat="49.774122" lon="13.405321">
			<ele>312.00</ele>
			<time>2020-11-07T14:52:46Z</time>
			<extensions>
				<gte:gps speed="0.0"/>
			</extensions>
		</trkpt>
		<trkpt lat="49.775928" lon="13.398748">
			<ele>312.00</ele>
			<time>2020-11-07T15:19:54Z</time>
			<extensions>
				<gte:gps speed="2.3"/>
			</extensions>
		</trkpt>
		<trkpt lat="49.778582" lon="13.392981">
			<ele>316.66</ele>
			<time>2020-11-07T15:26:48Z</time>
			<extensions>
				<gte:gps speed="5.5"/>
			</extensions>
		</trkpt>
		<trkpt lat="49.779764" lon="13.386198">
			<ele>332.00</ele>
			<time>2020-11-07T15:34:31Z</time>
			<extensions>
				<gte:gps speed="10.4"/>
			</extensions>
		</trkpt>
		<trkpt lat="49.776779" lon="13.380837">
			<ele>333.47</ele>
			<time>2020-11-07T15:41:59Z</time>
			<extensions>
				<gte:gps speed="5.1"/>
			</extensions>
		</trkpt>
		<trkpt lat="49.777660" lon="13.373896">
			<ele>360.06</ele>
			<time>2020-11-07T15:50:48Z</time>
			<extensions>
				<gte:gps speed="0.0"/>
			</extensions>
		</trkpt>
		<extensions>
			<gte:name>#1</gte:name>
			<gte:color>#fbaf00</gte:color>
		</extensions>
	</trkseg>
</trk>
</gpx>