<?xml version="1.0" encoding="UTF-8"?>
<gpx version="1.1" creator="GPS Track Editor" xmlns="http://www.topografix.com/GPX/1/1" xmlns:xsi="http://www.w3.org/2001/XMLSchema-instance" xmlns:gte="http://www.gpstrackeditor.com/xmlschemas/General/1" xmlns:gpxtpx="http://www.garmin.com/xmlschemas/TrackPointExtension/v1" xmlns:gpxx="http://www.garmin.com/xmlschemas/GpxExtensions/v3" targetNamespace="http://www.topografix.com/GPX/1/1" elementFormDefault="qualified" xsi:schemaLocation="http://www.topografix.com/GPX/1/1 http://www.topografix.com/GPX/1/1/gpx.xsd">
<metadata>
	<name>20210224 - Bavorov - Vodnany.gpx</name>
	<desc>18,386,-413
        </desc>
	<keywords>Monca, ja</keywords>
</metadata>
<trk>
	<name>20210224 - streda</name>
	<desc>Color:004000ff</desc>
	<trkseg>
		<trkpt lat="49.126278" lon="14.083591">
			<ele>427.87</ele>
			<time>2021-02-24T09:01:13Z</time>
			<extensions>
				<gte:gps speed="0.0"/>
			</extensions>
		</trkpt>
		<trkpt lat="49.123413" lon="14.089154">
			<ele>418.00</ele>
			<time>2021-02-24T09:20:38Z</time>
			<extensions>
				<gte:gps speed="5.4"/>
			</extensions>
		</trkpt>
		<trkpt lat="49.122741" lon="14.096271">
			<ele>443.50</ele>
			<time>2021-02-24T09:31:42Z</time>
			<extensions>
				<gte:gps speed="0.0"/>
			</extensions>
		</trkpt>
		<trkpt lat="49.120361" lon="14.102154">
			<ele>499.22</ele>
			<time>2021-02-24T09:58:23Z</time>
			<extensions>
				<gte:gps speed="3.7"/>
			</extensions>
		</trkpt>
		<trkpt lat="49.122552" lon="14.108226">
			<ele>572.90</ele>
			<time>2021-02-24T10:09:43Z</time>
			<extensions>
				<gte:gps speed="0.0"/>
			</extensions>
		</trkpt>
		<trkpt lat="49.122337" lon="14.115192">
			<ele>628.34</ele>
			<time>2021-02-24T10:21:53Z</time>
			<extensions>
				<gte:gps speed="0.0"/>
			</extensions>
		</trkpt>
		<trkpt lat="49.125530" lon="14.120115">
			<ele>602.00</ele>
			<time>2021-02-24T11:08:13Z</time>
			<extensions>
				<gte:gps speed="3.3"/>
			</extensions>
		</trkpt>
		<trkpt lat="49.125980" lon="14.127214">
			<ele>544.44</ele>
			<time>2021-02-24T11:18:10Z</time>
			<extensions>
				<gte:gps speed="0.0"/>
			</extensions>
		</trkpt>
		<trkpt lat="49.130341" lon="14.129264">
			<ele>511.18</ele>
			<time>2021-02-24T11:25:22Z</time>
			<extensions>
				<gte:gps speed="4.9"/>
			</extensions>
		</trkpt>
		<trkpt lat="49.132931" lon="14.123485">
			<ele>475.43</ele>
			<time>2021-02-24T11:33:17Z</time>
			<extensions>
				<gte:gps speed="0.0"/>
			</extensions>
		</trkpt>
		<trkpt lat="49.136459" lon="14.119163">
			<ele>432.65</ele>
			<time>2021-02-24T11:45:35Z</time>
			<extensions>
				<gte:gps speed="4.9"/>
			</extensions>
		</trkpt>
		<trkpt lat="49.140457" lon="14.115460">
			<ele>411.97</ele>
			<time>2021-02-24T11:54:14Z</time>
			<extensions>
				<gte:gps speed="4.0"/>
			</extensions>
		</trkpt>
		<trkpt lat="49.144766" lon="14.113200">
			<ele>408.00</ele>
			<time>2021-02-24T12:00:39.42Z</time>
		</trkpt>
		<trkpt lat="49.147760" lon="14.118613">
			<ele>406.00</ele>
			<time>2021-02-24T12:06:54Z</time>
			<extensions>
				<gte:gps speed="4.5"/>
			</extensions>
		</trkpt>
		<trkpt lat="49.148388" lon="14.125487">
			<ele>411.18</ele>
			<time>2021-02-24T12:20:54Z</time>
			<extensions>
				<gte:gps speed="0.0"/>
			</extensions>
		</trkpt>
		<trkpt lat="49.151890" lon="14.130134">
			<ele>429.35</ele>
			<time>2021-02-24T12:31:46Z</time>
			<extensions>
				<gte:gps speed="0.0"/>
			</extensions>
		</trkpt>
		<trkpt lat="49.156459" lon="14.129957">
			<ele>401.00</ele>
			<time>2021-02-24T12:41:40Z</time>
			<extensions>
				<gte:gps speed="5.2"/>
			</extensions>
		</trkpt>
		<trkpt lat="49.155352" lon="14.136791">
			<ele>400.00</ele>
			<time>2021-02-24T12:49:16Z</time>
			<extensions>
				<gte:gps speed="0.0"/>
			</extensions>
		</trkpt>
		<trkpt lat="49.155228" lon="14.143811">
			<ele>399.00</ele>
			<time>2021-02-24T12:55:12Z</time>
			<extensions>
				<gte:gps speed="0.0"/>
			</extensions>
		</trkpt>
		<trkpt lat="49.157467" lon="14.149958">
			<ele>396.00</ele>
			<time>2021-02-24T13:03:36Z</time>
			<extensions>
				<gte:gps speed="0.0"/>
			</extensions>
		</trkpt>
		<trkpt lat="49.158134" lon="14.156875">
			<ele>395.00</ele>
			<time>2021-02-24T13:12:52Z</time>
			<extensions>
				<gte:gps speed="0.0"/>
			</extensions>
		</trkpt>
		<trkpt lat="49.155896" lon="14.163217">
			<ele>394.00</ele>
			<time>2021-02-24T13:22:46Z</time>
			<extensions>
				<gte:gps speed="1.6"/>
			</extensions>
		</trkpt>
		<trkpt lat="49.153745" lon="14.169391">
			<ele>394.76</ele>
			<time>2021-02-24T13:28:46Z</time>
			<extensions>
				<gte:gps speed="4.3"/>
			</extensions>
		</trkpt>
		<trkpt lat="49.157341" lon="14.173603">
			<ele>393.76</ele>
			<time>2021-02-24T13:38:56Z</time>
			<extensions>
				<gte:gps speed="3.5"/>
			</extensions>
		</trkpt>
		<trkpt lat="49.161465" lon="14.176375">
			<ele>428.17</ele>
			<time>2021-02-24T14:00:25Z</time>
			<extensions>
				<gte:gps speed="2.6"/>
			</extensions>
		</trkpt>
		<trkpt lat="49.156807" lon="14.176271">
			<ele>392.12</ele>
			<time>2021-02-24T14:11:52Z</time>
			<extensions>
				<gte:gps speed="0.0"/>
			</extensions>
		</trkpt>
		<trkpt lat="49.152204" lon="14.175014">
			<ele>393.93</ele>
			<time>2021-02-24T14:18:01Z</time>
			<extensions>
				<gte:gps speed="5.1"/>
			</extensions>
		</trkpt>
		<trkpt lat="49.147705" lon="14.175529">
			<ele>402.00</ele>
			<time>2021-02-24T14:26:37Z</time>
			<extensions>
				<gte:gps speed="1.1"/>
			</extensions>
		</trkpt>
		<extensions>
			<gte:name>#1</gte:name>
			<gte:color>#fbaf00</gte:color>
		</extensions>
	</trkseg>
</trk>
</gpx>