<?xml version="1.0" encoding="UTF-8"?>
<gpx version="1.1" creator="GPS Track Editor" xmlns="http://www.topografix.com/GPX/1/1" xmlns:xsi="http://www.w3.org/2001/XMLSchema-instance" xmlns:gte="http://www.gpstrackeditor.com/xmlschemas/General/1" xmlns:gpxtpx="http://www.garmin.com/xmlschemas/TrackPointExtension/v1" xmlns:gpxx="http://www.garmin.com/xmlschemas/GpxExtensions/v3" targetNamespace="http://www.topografix.com/GPX/1/1" elementFormDefault="qualified" xsi:schemaLocation="http://www.topografix.com/GPX/1/1 http://www.topografix.com/GPX/1/1/gpx.xsd">
<metadata>
	<name>20240907-08 - Tabor - Tyn n. Vltavou.gpx</name>
	<desc>40,659,-733
        </desc>
	<keywords>Kabi, Lucka Ladrova, Monca, ja</keywords>
</metadata>
<trk>
	<name>20240907 - sobota</name>
	<desc>Color:004000ff</desc>
	<trkseg>
		<trkpt lat="49.411308" lon="14.656767">
			<ele>433.72</ele>
			<time>2024-09-07T06:32:27Z</time>
			<extensions>
				<gte:gps speed="9.5"/>
			</extensions>
		</trkpt>
		<trkpt lat="49.408665" lon="14.650955">
			<ele>407.13</ele>
			<time>2024-09-07T06:41:19Z</time>
			<extensions>
				<gte:gps speed="2.2"/>
			</extensions>
		</trkpt>
		<trkpt lat="49.411914" lon="14.646109">
			<ele>395.21</ele>
			<time>2024-09-07T06:57:26Z</time>
			<extensions>
				<gte:gps speed="3.8"/>
			</extensions>
		</trkpt>
		<trkpt lat="49.410285" lon="14.639418">
			<ele>387.95</ele>
			<time>2024-09-07T07:04:59Z</time>
			<extensions>
				<gte:gps speed="2.7"/>
			</extensions>
		</trkpt>
		<trkpt lat="49.411324" lon="14.632600">
			<ele>385.08</ele>
			<time>2024-09-07T07:14:10Z</time>
			<extensions>
				<gte:gps speed="5.0"/>
			</extensions>
		</trkpt>
		<trkpt lat="49.407894" lon="14.628099">
			<ele>384.45</ele>
			<time>2024-09-07T07:21:41Z</time>
			<extensions>
				<gte:gps speed="3.0"/>
			</extensions>
		</trkpt>
		<trkpt lat="49.411826" lon="14.623311">
			<ele>383.82</ele>
			<time>2024-09-07T07:31:31.40Z</time>
		</trkpt>
		<trkpt lat="49.412649" lon="14.615657">
			<ele>381.29</ele>
			<time>2024-09-07T07:41:05Z</time>
			<extensions>
				<gte:gps speed="3.9"/>
			</extensions>
		</trkpt>
		<trkpt lat="49.412206" lon="14.608690">
			<ele>381.83</ele>
			<time>2024-09-07T07:52:46.37Z</time>
		</trkpt>
		<trkpt lat="49.409086" lon="14.603109">
			<ele>387.69</ele>
			<time>2024-09-07T08:08:13.75Z</time>
		</trkpt>
		<trkpt lat="49.407376" lon="14.596260">
			<ele>376.20</ele>
			<time>2024-09-07T08:16:47.29Z</time>
		</trkpt>
		<trkpt lat="49.403772" lon="14.591535">
			<ele>374.15</ele>
			<time>2024-09-07T08:25:51Z</time>
		</trkpt>
		<trkpt lat="49.401362" lon="14.585367">
			<ele>373.04</ele>
			<time>2024-09-07T08:34:13.01Z</time>
		</trkpt>
		<trkpt lat="49.396944" lon="14.582218">
			<ele>378.95</ele>
			<time>2024-09-07T08:43:24.85Z</time>
		</trkpt>
		<trkpt lat="49.396533" lon="14.574259">
			<ele>374.81</ele>
			<time>2024-09-07T08:51:09.93Z</time>
		</trkpt>
		<trkpt lat="49.393886" lon="14.567941">
			<ele>387.32</ele>
			<time>2024-09-07T08:59:12.20Z</time>
		</trkpt>
		<trkpt lat="49.393688" lon="14.560826">
			<ele>385.02</ele>
			<time>2024-09-07T09:04:56.82Z</time>
		</trkpt>
		<trkpt lat="49.389129" lon="14.562932">
			<ele>376.97</ele>
			<time>2024-09-07T10:06:26Z</time>
			<extensions>
				<gte:gps speed="2.1"/>
			</extensions>
		</trkpt>
		<trkpt lat="49.385803" lon="14.557799">
			<ele>376.02</ele>
			<time>2024-09-07T10:14:02Z</time>
			<extensions>
				<gte:gps speed="3.4"/>
			</extensions>
		</trkpt>
		<trkpt lat="49.386312" lon="14.550666">
			<ele>387.93</ele>
			<time>2024-09-07T10:23:21Z</time>
			<extensions>
				<gte:gps speed="1.8"/>
			</extensions>
		</trkpt>
		<trkpt lat="49.384115" lon="14.544607">
			<ele>381.57</ele>
			<time>2024-09-07T10:33:52Z</time>
			<extensions>
				<gte:gps speed="0.0"/>
			</extensions>
		</trkpt>
		<trkpt lat="49.381580" lon="14.538756">
			<ele>370.94</ele>
			<time>2024-09-07T10:40:30Z</time>
			<extensions>
				<gte:gps speed="0.0"/>
			</extensions>
		</trkpt>
		<trkpt lat="49.379286" lon="14.532141">
			<ele>373.59</ele>
			<time>2024-09-07T10:49:32Z</time>
			<extensions>
				<gte:gps speed="3.1"/>
			</extensions>
		</trkpt>
		<trkpt lat="49.374671" lon="14.529498">
			<ele>376.93</ele>
			<time>2024-09-07T11:02:18Z</time>
			<extensions>
				<gte:gps speed="1.6"/>
			</extensions>
		</trkpt>
		<trkpt lat="49.371344" lon="14.524643">
			<ele>371.24</ele>
			<time>2024-09-07T11:10:06.91Z</time>
		</trkpt>
		<trkpt lat="49.369126" lon="14.518322">
			<ele>374.08</ele>
			<time>2024-09-07T11:19:32.44Z</time>
		</trkpt>
		<trkpt lat="49.366116" lon="14.512444">
			<ele>368.21</ele>
			<time>2024-09-07T11:31:00Z</time>
			<extensions>
				<gte:gps speed="6.2"/>
			</extensions>
		</trkpt>
		<trkpt lat="49.361533" lon="14.513394">
			<ele>367.51</ele>
			<time>2024-09-07T11:39:34Z</time>
			<extensions>
				<gte:gps speed="3.1"/>
			</extensions>
		</trkpt>
		<trkpt lat="49.356765" lon="14.514486">
			<ele>367.87</ele>
			<time>2024-09-07T11:46:59Z</time>
			<extensions>
				<gte:gps speed="2.7"/>
			</extensions>
		</trkpt>
		<trkpt lat="49.352421" lon="14.511373">
			<ele>368.77</ele>
			<time>2024-09-07T12:16:57Z</time>
			<extensions>
				<gte:gps speed="4.8"/>
			</extensions>
		</trkpt>
		<trkpt lat="49.347711" lon="14.511267">
			<ele>373.29</ele>
			<time>2024-09-07T12:24:54Z</time>
			<extensions>
				<gte:gps speed="6.4"/>
			</extensions>
		</trkpt>
		<trkpt lat="49.346671" lon="14.504290">
			<ele>383.97</ele>
			<time>2024-09-07T12:32:39Z</time>
			<extensions>
				<gte:gps speed="4.4"/>
			</extensions>
		</trkpt>
		<trkpt lat="49.342949" lon="14.500379">
			<ele>415.92</ele>
			<time>2024-09-07T12:47:50Z</time>
			<extensions>
				<gte:gps speed="3.6"/>
			</extensions>
		</trkpt>
		<trkpt lat="49.338341" lon="14.501043">
			<ele>366.72</ele>
			<time>2024-09-07T13:20:32.95Z</time>
		</trkpt>
		<trkpt lat="49.333956" lon="14.499114">
			<ele>365.65</ele>
			<time>2024-09-07T14:10:57.74Z</time>
		</trkpt>
		<trkpt lat="49.333031" lon="14.491934">
			<ele>365.35</ele>
			<time>2024-09-07T14:16:58Z</time>
			<extensions>
				<gte:gps speed="6.8"/>
			</extensions>
		</trkpt>
		<trkpt lat="49.331410" lon="14.485152">
			<ele>363.62</ele>
			<time>2024-09-07T14:23:57Z</time>
			<extensions>
				<gte:gps speed="0.0"/>
			</extensions>
		</trkpt>
		<trkpt lat="49.326789" lon="14.485258">
			<ele>365.82</ele>
			<time>2024-09-07T14:33:49Z</time>
			<extensions>
				<gte:gps speed="2.6"/>
			</extensions>
		</trkpt>
		<trkpt lat="49.323012" lon="14.489127">
			<ele>364.65</ele>
			<time>2024-09-07T14:41:19Z</time>
			<extensions>
				<gte:gps speed="2.1"/>
			</extensions>
		</trkpt>
		<trkpt lat="49.318923" lon="14.492678">
			<ele>364.96</ele>
			<time>2024-09-07T14:50:40Z</time>
			<extensions>
				<gte:gps speed="3.2"/>
			</extensions>
		</trkpt>
		<trkpt lat="49.314384" lon="14.494503">
			<ele>397.73</ele>
			<time>2024-09-07T15:06:36Z</time>
			<extensions>
				<gte:gps speed="2.7"/>
			</extensions>
		</trkpt>
		<trkpt lat="49.311020" lon="14.489816">
			<ele>398.59</ele>
			<time>2024-09-07T15:16:35Z</time>
			<extensions>
				<gte:gps speed="2.9"/>
			</extensions>
		</trkpt>
		<trkpt lat="49.306728" lon="14.487260">
			<ele>418.27</ele>
			<time>2024-09-07T15:39:08Z</time>
			<extensions>
				<gte:gps speed="5.4"/>
			</extensions>
		</trkpt>
		<trkpt lat="49.304274" lon="14.481292">
			<ele>424.48</ele>
			<time>2024-09-07T15:45:20Z</time>
			<extensions>
				<gte:gps speed="5.1"/>
			</extensions>
		</trkpt>
		<trkpt lat="49.301490" lon="14.475441">
			<ele>414.80</ele>
			<time>2024-09-07T15:51:41Z</time>
			<extensions>
				<gte:gps speed="4.3"/>
			</extensions>
		</trkpt>
		<extensions>
			<gte:name>#1</gte:name>
			<gte:color>#fbaf00</gte:color>
		</extensions>
	</trkseg>
</trk>
<trk>
	<name>20240908 - nedele</name>
	<desc>Color:004000ff</desc>
	<trkseg>
		<trkpt lat="49.299104" lon="14.471979">
			<ele>410.23</ele>
			<time>2024-09-08T06:12:33Z</time>
			<extensions>
				<gte:gps speed="5.5"/>
			</extensions>
		</trkpt>
		<trkpt lat="49.295142" lon="14.468524">
			<ele>404.34</ele>
			<time>2024-09-08T06:16:26Z</time>
			<extensions>
				<gte:gps speed="4.3"/>
			</extensions>
		</trkpt>
		<trkpt lat="49.290624" lon="14.466880">
			<ele>385.51</ele>
			<time>2024-09-08T06:25:15Z</time>
			<extensions>
				<gte:gps speed="5.5"/>
			</extensions>
		</trkpt>
		<trkpt lat="49.286265" lon="14.468923">
			<ele>358.28</ele>
			<time>2024-09-08T06:37:33Z</time>
			<extensions>
				<gte:gps speed="3.7"/>
			</extensions>
		</trkpt>
		<trkpt lat="49.282606" lon="14.464211">
			<ele>360.83</ele>
			<time>2024-09-08T06:49:49Z</time>
			<extensions>
				<gte:gps speed="5.1"/>
			</extensions>
		</trkpt>
		<trkpt lat="49.279289" lon="14.458966">
			<ele>359.18</ele>
			<time>2024-09-08T06:57:54Z</time>
			<extensions>
				<gte:gps speed="3.5"/>
			</extensions>
		</trkpt>
		<trkpt lat="49.279403" lon="14.451849">
			<ele>356.83</ele>
			<time>2024-09-08T07:05:07Z</time>
			<extensions>
				<gte:gps speed="3.6"/>
			</extensions>
		</trkpt>
		<trkpt lat="49.279072" lon="14.444674">
			<ele>356.36</ele>
			<time>2024-09-08T07:11:59Z</time>
			<extensions>
				<gte:gps speed="0.0"/>
			</extensions>
		</trkpt>
		<trkpt lat="49.277624" lon="14.438112">
			<ele>357.03</ele>
			<time>2024-09-08T07:17:49Z</time>
			<extensions>
				<gte:gps speed="9.6"/>
			</extensions>
		</trkpt>
		<trkpt lat="49.274181" lon="14.433405">
			<ele>355.00</ele>
			<time>2024-09-08T07:24:05Z</time>
			<extensions>
				<gte:gps speed="5.3"/>
			</extensions>
		</trkpt>
		<trkpt lat="49.270351" lon="14.429469">
			<ele>354.81</ele>
			<time>2024-09-08T07:33:14Z</time>
			<extensions>
				<gte:gps speed="8.6"/>
			</extensions>
		</trkpt>
		<trkpt lat="49.265897" lon="14.427626">
			<ele>352.97</ele>
			<time>2024-09-08T07:39:11Z</time>
			<extensions>
				<gte:gps speed="4.6"/>
			</extensions>
		</trkpt>
		<trkpt lat="49.261241" lon="14.428188">
			<ele>353.68</ele>
			<time>2024-09-08T07:45:59Z</time>
			<extensions>
				<gte:gps speed="5.5"/>
			</extensions>
		</trkpt>
		<trkpt lat="49.257059" lon="14.425126">
			<ele>354.28</ele>
			<time>2024-09-08T07:52:57Z</time>
			<extensions>
				<gte:gps speed="5.0"/>
			</extensions>
		</trkpt>
		<trkpt lat="49.253601" lon="14.420135">
			<ele>354.83</ele>
			<time>2024-09-08T08:33:27Z</time>
			<extensions>
				<gte:gps speed="3.1"/>
			</extensions>
		</trkpt>
		<trkpt lat="49.249077" lon="14.420410">
			<ele>362.70</ele>
			<time>2024-09-08T08:41:19Z</time>
			<extensions>
				<gte:gps speed="3.0"/>
			</extensions>
		</trkpt>
		<trkpt lat="49.246431" lon="14.414699">
			<ele>355.02</ele>
			<time>2024-09-08T08:48:59Z</time>
			<extensions>
				<gte:gps speed="11.2"/>
			</extensions>
		</trkpt>
		<trkpt lat="49.242643" lon="14.410607">
			<ele>403.71</ele>
			<time>2024-09-08T08:58:02Z</time>
			<extensions>
				<gte:gps speed="7.2"/>
			</extensions>
		</trkpt>
		<trkpt lat="49.238163" lon="14.412735">
			<ele>409.29</ele>
			<time>2024-09-08T09:05:48Z</time>
			<extensions>
				<gte:gps speed="5.3"/>
			</extensions>
		</trkpt>
		<trkpt lat="49.233826" lon="14.409254">
			<ele>439.00</ele>
			<time>2024-09-08T09:12:41Z</time>
			<extensions>
				<gte:gps speed="7.4"/>
			</extensions>
		</trkpt>
		<trkpt lat="49.229626" lon="14.412580">
			<ele>403.11</ele>
			<time>2024-09-08T09:28:22Z</time>
			<extensions>
				<gte:gps speed="4.9"/>
			</extensions>
		</trkpt>
		<trkpt lat="49.224991" lon="14.413764">
			<ele>353.19</ele>
			<time>2024-09-08T09:38:08Z</time>
			<extensions>
				<gte:gps speed="6.6"/>
			</extensions>
		</trkpt>
		<extensions>
			<gte:name>#2</gte:name>
			<gte:color>#00ce00</gte:color>
		</extensions>
	</trkseg>
</trk>
</gpx>